{"crate":{"id":"openssl","name":"openssl","updated_at":"2018-12-16T17:04:47.852785+00:00","versions":[122641,113991,113549,112811,108171,102379,95665,95116,93613,90980,87737,82841,81588,80904,77158,77082,77081,80908,73433,72688,71609,68352,65869,65842,62397,62114,60158,56768,55138,53134,50306,48782,47809,47398,45246,42023,41517,40256,39346,38644,37669,37347,33378,32000,31811,31656,29434,27465,27249,26644,25716,25161,24106,24066,22170,21164,19565,19527,19443,18678,18208,16708,16450,15319,12758,12295,9641,9202,8195,7959,7798,7480,7118,5996,5747,5276,5217,5134,5042,4948,4891,4886,4776,4774,4401,4387,4021,3357,3044,2630,2423,2335,2130,1994,1871,1798,1578,1467,1367,1208,1168,1029,764,727,701,650,631,581,321],"keywords":["tls","ssl","dtls","crypto"],"categories":["cryptography","api-bindings"],"badges":[],"created_at":"2014-11-21T06:54:00.684701+00:00","downloads":2840207,"recent_downloads":502365,"max_version":"0.10.16","description":"OpenSSL bindings","homepage":null,"documentation":null,"repository":"https://github.com/sfackler/rust-openssl","links":{"version_downloads":"/api/v1/crates/openssl/downloads","versions":null,"owners":"/api/v1/crates/openssl/owners","owner_team":"/api/v1/crates/openssl/owner_team","owner_user":"/api/v1/crates/openssl/owner_user","reverse_dependencies":"/api/v1/crates/openssl/reverse_dependencies"},"exact_match":false},"versions":[{"id":122641,"crate":"openssl","num":"0.10.16","dl_path":"/api/v1/crates/openssl/0.10.16/download","readme_path":"/api/v1/crates/openssl/0.10.16/readme","updated_at":"2018-12-16T17:04:47.852785+00:00","created_at":"2018-12-16T17:04:47.852785+00:00","downloads":64464,"features":{"v101":[],"v102":[],"v110":[],"v111":[],"vendored":["openssl-sys/vendored"]},"yanked":false,"license":"Apache-2.0","links":{"dependencies":"/api/v1/crates/openssl/0.10.16/dependencies","version_downloads":"/api/v1/crates/openssl/0.10.16/downloads","authors":"/api/v1/crates/openssl/0.10.16/authors"},"crate_size":168681},{"id":113991,"crate":"openssl","num":"0.10.15","dl_path":"/api/v1/crates/openssl/0.10.15/download","readme_path":"/api/v1/crates/openssl/0.10.15/readme","updated_at":"2018-10-22T16:04:48.167117+00:00","created_at":"2018-10-22T16:04:48.167117+00:00","downloads":172220,"features":{"v101":[],"v102":[],"v110":[],"v111":[],"vendored":["openssl-sys/vendored"]},"yanked":false,"license":"Apache-2.0","links":{"dependencies":"/api/v1/crates/openssl/0.10.15/dependencies","version_downloads":"/api/v1/crates/openssl/0.10.15/downloads","authors":"/api/v1/crates/openssl/0.10.15/authors"},"crate_size":167961},{"id":113549,"crate":"openssl","num":"0.10.14","dl_path":"/api/v1/crates/openssl/0.10.14/download","readme_path":"/api/v1/crates/openssl/0.10.14/readme","updated_at":"2018-10-19T03:17:12.526210+00:00","created_at":"2018-10-19T03:17:12.526210+00:00","downloads":8913,"features":{"v101":[],"v102":[],"v110":[],"v111":[],"vendored":["openssl-sys/vendored"]},"yanked":false,"license":"Apache-2.0","links":{"dependencies":"/api/v1/crates/openssl/0.10.14/dependencies","version_downloads":"/api/v1/crates/openssl/0.10.14/downloads","authors":"/api/v1/crates/openssl/0.10.14/authors"},"crate_size":168129},{"id":112811,"crate":"openssl","num":"0.10.13","dl_path":"/api/v1/crates/openssl/0.10.13/download","readme_path":"/api/v1/crates/openssl/0.10.13/readme","updated_at":"2018-10-14T23:10:49.121596+00:00","created_at":"2018-10-14T23:10:49.121596+00:00","downloads":57236,"features":{"v101":[],"v102":[],"v110":[],"v111":[],"vendored":["openssl-sys/vendored"]},"yanked":false,"license":"Apache-2.0","links":{"dependencies":"/api/v1/crates/openssl/0.10.13/dependencies","version_downloads":"/api/v1/crates/openssl/0.10.13/downloads","authors":"/api/v1/crates/openssl/0.10.13/authors"},"crate_size":168115},{"id":108171,"crate":"openssl","num":"0.10.12","dl_path":"/api/v1/crates/openssl/0.10.12/download","readme_path":"/api/v1/crates/openssl/0.10.12/readme","updated_at":"2018-09-14T02:23:29.327596+00:00","created_at":"2018-09-14T02:23:29.327596+00:00","downloads":88030,"features":{"v101":[],"v102":[],"v110":[],"v111":[],"vendored":["openssl-sys/vendored"]},"yanked":false,"license":"Apache-2.0","links":{"dependencies":"/api/v1/crates/openssl/0.10.12/dependencies","version_downloads":"/api/v1/crates/openssl/0.10.12/downloads","authors":"/api/v1/crates/openssl/0.10.12/authors"},"crate_size":165851},{"id":102379,"crate":"openssl","num":"0.10.11","dl_path":"/api/v1/crates/openssl/0.10.11/download","readme_path":"/api/v1/crates/openssl/0.10.11/readme","updated_at":"2018-08-04T17:13:17.609917+00:00","created_at":"2018-08-04T17:13:17.609917+00:00","downloads":110600,"features":{"v101":[],"v102":[],"v110":[],"v111":[],"vendored":["openssl-sys/vendored"]},"yanked":false,"license":"Apache-2.0","links":{"dependencies":"/api/v1/crates/openssl/0.10.11/dependencies","version_downloads":"/api/v1/crates/openssl/0.10.11/downloads","authors":"/api/v1/crates/openssl/0.10.11/authors"},"crate_size":null},{"id":95665,"crate":"openssl","num":"0.10.10","dl_path":"/api/v1/crates/openssl/0.10.10/download","readme_path":"/api/v1/crates/openssl/0.10.10/readme","updated_at":"2018-06-06T20:37:44.923014+00:00","created_at":"2018-06-06T20:37:44.923014+00:00","downloads":85813,"features":{"v101":[],"v102":[],"v110":[],"v111":[]},"yanked":false,"license":"Apache-2.0","links":{"dependencies":"/api/v1/crates/openssl/0.10.10/dependencies","version_downloads":"/api/v1/crates/openssl/0.10.10/downloads","authors":"/api/v1/crates/openssl/0.10.10/authors"},"crate_size":null},{"id":95116,"crate":"openssl","num":"0.10.9","dl_path":"/api/v1/crates/openssl/0.10.9/download","readme_path":"/api/v1/crates/openssl/0.10.9/readme","updated_at":"2018-06-02T03:59:46.478806+00:00","created_at":"2018-06-02T03:59:46.478806+00:00","downloads":3320,"features":{"v101":[],"v102":[],"v110":[],"v111":[]},"yanked":false,"license":"Apache-2.0","links":{"dependencies":"/api/v1/crates/openssl/0.10.9/dependencies","version_downloads":"/api/v1/crates/openssl/0.10.9/downloads","authors":"/api/v1/crates/openssl/0.10.9/authors"},"crate_size":null},{"id":93613,"crate":"openssl","num":"0.10.8","dl_path":"/api/v1/crates/openssl/0.10.8/download","readme_path":"/api/v1/crates/openssl/0.10.8/readme","updated_at":"2018-05-21T04:03:34.395453+00:00","created_at":"2018-05-21T04:03:34.395453+00:00","downloads":8231,"features":{"v101":[],"v102":[],"v110":[],"v111":[]},"yanked":false,"license":"Apache-2.0","links":{"dependencies":"/api/v1/crates/openssl/0.10.8/dependencies","version_downloads":"/api/v1/crates/openssl/0.10.8/downloads","authors":"/api/v1/crates/openssl/0.10.8/authors"},"crate_size":null},{"id":90980,"crate":"openssl","num":"0.10.7","dl_path":"/api/v1/crates/openssl/0.10.7/download","readme_path":"/api/v1/crates/openssl/0.10.7/readme","updated_at":"2018-05-01T03:41:50.213588+00:00","created_at":"2018-05-01T03:41:50.213588+00:00","downloads":14874,"features":{"v101":[],"v102":[],"v110":[],"v111":[]},"yanked":false,"license":"Apache-2.0","links":{"dependencies":"/api/v1/crates/openssl/0.10.7/dependencies","version_downloads":"/api/v1/crates/openssl/0.10.7/downloads","authors":"/api/v1/crates/openssl/0.10.7/authors"},"crate_size":null},{"id":87737,"crate":"openssl","num":"0.10.6","dl_path":"/api/v1/crates/openssl/0.10.6/download","readme_path":"/api/v1/crates/openssl/0.10.6/readme","updated_at":"2018-04-05T18:12:26.599960+00:00","created_at":"2018-04-05T18:12:26.599960+00:00","downloads":93688,"features":{"v101":[],"v102":[],"v110":[],"v111":[]},"yanked":false,"license":"Apache-2.0","links":{"dependencies":"/api/v1/crates/openssl/0.10.6/dependencies","version_downloads":"/api/v1/crates/openssl/0.10.6/downloads","authors":"/api/v1/crates/openssl/0.10.6/authors"},"crate_size":null},{"id":82841,"crate":"openssl","num":"0.10.5","dl_path":"/api/v1/crates/openssl/0.10.5/download","readme_path":"/api/v1/crates/openssl/0.10.5/readme","updated_at":"2018-02-28T22:33:26.057894+00:00","created_at":"2018-02-28T22:33:26.057894+00:00","downloads":44984,"features":{"v101":[],"v102":[],"v110":[],"v111":[]},"yanked":false,"license":"Apache-2.0","links":{"dependencies":"/api/v1/crates/openssl/0.10.5/dependencies","version_downloads":"/api/v1/crates/openssl/0.10.5/downloads","authors":"/api/v1/crates/openssl/0.10.5/authors"},"crate_size":null},{"id":81588,"crate":"openssl","num":"0.10.4","dl_path":"/api/v1/crates/openssl/0.10.4/download","readme_path":"/api/v1/crates/openssl/0.10.4/readme","updated_at":"2018-02-18T18:50:25.875883+00:00","created_at":"2018-02-18T18:50:25.875883+00:00","downloads":955,"features":{"v101":[],"v102":[],"v110":[],"v111":[]},"yanked":false,"license":"Apache-2.0","links":{"dependencies":"/api/v1/crates/openssl/0.10.4/dependencies","version_downloads":"/api/v1/crates/openssl/0.10.4/downloads","authors":"/api/v1/crates/openssl/0.10.4/authors"},"crate_size":null},{"id":80904,"crate":"openssl","num":"0.10.3","dl_path":"/api/v1/crates/openssl/0.10.3/download","readme_path":"/api/v1/crates/openssl/0.10.3/readme","updated_at":"2018-02-12T18:56:38.024558+00:00","created_at":"2018-02-12T18:56:38.024558+00:00","downloads":559,"features":{"v101":[],"v102":[],"v110":[]},"yanked":false,"license":"Apache-2.0","links":{"dependencies":"/api/v1/crates/openssl/0.10.3/dependencies","version_downloads":"/api/v1/crates/openssl/0.10.3/downloads","authors":"/api/v1/crates/openssl/0.10.3/authors"},"crate_size":null},{"id":77158,"crate":"openssl","num":"0.10.2","dl_path":"/api/v1/crates/openssl/0.10.2/download","readme_path":"/api/v1/crates/openssl/0.10.2/readme","updated_at":"2018-01-12T01:34:39.044939+00:00","created_at":"2018-01-12T01:34:39.044939+00:00","downloads":2398,"features":{"v101":[],"v102":[],"v110":[]},"yanked":false,"license":"Apache-2.0","links":{"dependencies":"/api/v1/crates/openssl/0.10.2/dependencies","version_downloads":"/api/v1/crates/openssl/0.10.2/downloads","authors":"/api/v1/crates/openssl/0.10.2/authors"},"crate_size":null},{"id":77082,"crate":"openssl","num":"0.10.1","dl_path":"/api/v1/crates/openssl/0.10.1/download","readme_path":"/api/v1/crates/openssl/0.10.1/readme","updated_at":"2018-01-11T06:30:26.972491+00:00","created_at":"2018-01-11T06:30:26.972491+00:00","downloads":174,"features":{"v101":[],"v102":[],"v110":[]},"yanked":false,"license":"Apache-2.0","links":{"dependencies":"/api/v1/crates/openssl/0.10.1/dependencies","version_downloads":"/api/v1/crates/openssl/0.10.1/downloads","authors":"/api/v1/crates/openssl/0.10.1/authors"},"crate_size":null},{"id":77081,"crate":"openssl","num":"0.10.0","dl_path":"/api/v1/crates/openssl/0.10.0/download","readme_path":"/api/v1/crates/openssl/0.10.0/readme","updated_at":"2018-01-11T06:08:30.148077+00:00","created_at":"2018-01-11T06:08:30.148077+00:00","downloads":393,"features":{"v101":[],"v102":[],"v110":[]},"yanked":false,"license":"Apache-2.0","links":{"dependencies":"/api/v1/crates/openssl/0.10.0/dependencies","version_downloads":"/api/v1/crates/openssl/0.10.0/downloads","authors":"/api/v1/crates/openssl/0.10.0/authors"},"crate_size":null},{"id":80908,"crate":"openssl","num":"0.9.24","dl_path":"/api/v1/crates/openssl/0.9.24/download","readme_path":"/api/v1/crates/openssl/0.9.24/readme","updated_at":"2018-02-12T19:19:35.753989+00:00","created_at":"2018-02-12T19:19:35.753989+00:00","downloads":408373,"features":{"v101":[],"v102":[],"v110":[]},"yanked":false,"license":"Apache-2.0","links":{"dependencies":"/api/v1/crates/openssl/0.9.24/dependencies","version_downloads":"/api/v1/crates/openssl/0.9.24/downloads","authors":"/api/v1/crates/openssl/0.9.24/authors"},"crate_size":null},{"id":73433,"crate":"openssl","num":"0.9.23","dl_path":"/api/v1/crates/openssl/0.9.23/download","readme_path":"/api/v1/crates/openssl/0.9.23/readme","updated_at":"2017-12-06T05:59:05.484848+00:00","created_at":"2017-12-06T05:59:05.484848+00:00","downloads":218637,"features":{"v101":[],"v102":[],"v110":[]},"yanked":false,"license":"Apache-2.0","links":{"dependencies":"/api/v1/crates/openssl/0.9.23/dependencies","version_downloads":"/api/v1/crates/openssl/0.9.23/downloads","authors":"/api/v1/crates/openssl/0.9.23/authors"},"crate_size":null},{"id":72688,"crate":"openssl","num":"0.9.22","dl_path":"/api/v1/crates/openssl/0.9.22/download","readme_path":"/api/v1/crates/openssl/0.9.22/readme","updated_at":"2017-11-30T02:25:28.205402+00:00","created_at":"2017-11-29T17:38:47.001432+00:00","downloads":36913,"features":{"v101":[],"v102":[],"v110":[]},"yanked":false,"license":"Apache-2.0","links":{"dependencies":"/api/v1/crates/openssl/0.9.22/dependencies","version_downloads":"/api/v1/crates/openssl/0.9.22/downloads","authors":"/api/v1/crates/openssl/0.9.22/authors"},"crate_size":null},{"id":71609,"crate":"openssl","num":"0.9.21","dl_path":"/api/v1/crates/openssl/0.9.21/download","readme_path":"/api/v1/crates/openssl/0.9.21/readme","updated_at":"2017-11-30T02:27:01.571991+00:00","created_at":"2017-11-17T17:16:50.709164+00:00","downloads":40219,"features":{"v101":[],"v102":[],"v110":[]},"yanked":false,"license":"Apache-2.0","links":{"dependencies":"/api/v1/crates/openssl/0.9.21/dependencies","version_downloads":"/api/v1/crates/openssl/0.9.21/downloads","authors":"/api/v1/crates/openssl/0.9.21/authors"},"crate_size":null},{"id":68352,"crate":"openssl","num":"0.9.20","dl_path":"/api/v1/crates/openssl/0.9.20/download","readme_path":"/api/v1/crates/openssl/0.9.20/readme","updated_at":"2017-11-30T02:51:47.803941+00:00","created_at":"2017-10-14T21:37:27.540623+00:00","downloads":60463,"features":{"v101":[],"v102":[],"v110":[]},"yanked":false,"license":"Apache-2.0","links":{"dependencies":"/api/v1/crates/openssl/0.9.20/dependencies","version_downloads":"/api/v1/crates/openssl/0.9.20/downloads","authors":"/api/v1/crates/openssl/0.9.20/authors"},"crate_size":null},{"id":65869,"crate":"openssl","num":"0.9.19","dl_path":"/api/v1/crates/openssl/0.9.19/download","readme_path":"/api/v1/crates/openssl/0.9.19/readme","updated_at":"2017-11-30T02:48:38.348134+00:00","created_at":"2017-09-20T20:51:44.153442+00:00","downloads":70085,"features":{"v101":[],"v102":[],"v110":[]},"yanked":false,"license":"Apache-2.0","links":{"dependencies":"/api/v1/crates/openssl/0.9.19/dependencies","version_downloads":"/api/v1/crates/openssl/0.9.19/downloads","authors":"/api/v1/crates/openssl/0.9.19/authors"},"crate_size":null},{"id":65842,"crate":"openssl","num":"0.9.18","dl_path":"/api/v1/crates/openssl/0.9.18/download","readme_path":"/api/v1/crates/openssl/0.9.18/readme","updated_at":"2017-11-30T03:24:37.234483+00:00","created_at":"2017-09-20T14:24:40.939726+00:00","downloads":1503,"features":{"v101":[],"v102":[],"v110":[]},"yanked":false,"license":"Apache-2.0","links":{"dependencies":"/api/v1/crates/openssl/0.9.18/dependencies","version_downloads":"/api/v1/crates/openssl/0.9.18/downloads","authors":"/api/v1/crates/openssl/0.9.18/authors"},"crate_size":null},{"id":62397,"crate":"openssl","num":"0.9.17","dl_path":"/api/v1/crates/openssl/0.9.17/download","readme_path":"/api/v1/crates/openssl/0.9.17/readme","updated_at":"2017-11-30T03:19:01.000548+00:00","created_at":"2017-08-15T00:14:27.377679+00:00","downloads":60034,"features":{"v101":[],"v102":[],"v110":[]},"yanked":false,"license":"Apache-2.0","links":{"dependencies":"/api/v1/crates/openssl/0.9.17/dependencies","version_downloads":"/api/v1/crates/openssl/0.9.17/downloads","authors":"/api/v1/crates/openssl/0.9.17/authors"},"crate_size":null},{"id":62114,"crate":"openssl","num":"0.9.16","dl_path":"/api/v1/crates/openssl/0.9.16/download","readme_path":"/api/v1/crates/openssl/0.9.16/readme","updated_at":"2017-11-30T03:36:43.319724+00:00","created_at":"2017-08-11T05:18:20.276748+00:00","downloads":6665,"features":{"v101":[],"v102":[],"v110":[]},"yanked":false,"license":"Apache-2.0","links":{"dependencies":"/api/v1/crates/openssl/0.9.16/dependencies","version_downloads":"/api/v1/crates/openssl/0.9.16/downloads","authors":"/api/v1/crates/openssl/0.9.16/authors"},"crate_size":null},{"id":60158,"crate":"openssl","num":"0.9.15","dl_path":"/api/v1/crates/openssl/0.9.15/download","readme_path":"/api/v1/crates/openssl/0.9.15/readme","updated_at":"2017-11-30T03:16:16.968073+00:00","created_at":"2017-07-20T02:36:16.254229+00:00","downloads":56041,"features":{"v101":[],"v102":[],"v110":[]},"yanked":false,"license":"Apache-2.0","links":{"dependencies":"/api/v1/crates/openssl/0.9.15/dependencies","version_downloads":"/api/v1/crates/openssl/0.9.15/downloads","authors":"/api/v1/crates/openssl/0.9.15/authors"},"crate_size":null},{"id":56768,"crate":"openssl","num":"0.9.14","dl_path":"/api/v1/crates/openssl/0.9.14/download","readme_path":"/api/v1/crates/openssl/0.9.14/readme","updated_at":"2017-11-30T03:19:24.362870+00:00","created_at":"2017-06-15T03:00:20.779413+00:00","downloads":69660,"features":{"v101":[],"v102":[],"v110":[]},"yanked":false,"license":"Apache-2.0","links":{"dependencies":"/api/v1/crates/openssl/0.9.14/dependencies","version_downloads":"/api/v1/crates/openssl/0.9.14/downloads","authors":"/api/v1/crates/openssl/0.9.14/authors"},"crate_size":null},{"id":55138,"crate":"openssl","num":"0.9.13","dl_path":"/api/v1/crates/openssl/0.9.13/download","readme_path":"/api/v1/crates/openssl/0.9.13/readme","updated_at":"2017-11-30T03:18:48.130873+00:00","created_at":"2017-05-30T00:46:52.773332+00:00","downloads":41261,"features":{"v101":[],"v102":[],"v110":[]},"yanked":false,"license":"Apache-2.0","links":{"dependencies":"/api/v1/crates/openssl/0.9.13/dependencies","version_downloads":"/api/v1/crates/openssl/0.9.13/downloads","authors":"/api/v1/crates/openssl/0.9.13/authors"},"crate_size":null},{"id":53134,"crate":"openssl","num":"0.9.12","dl_path":"/api/v1/crates/openssl/0.9.12/download","readme_path":"/api/v1/crates/openssl/0.9.12/readme","updated_at":"2017-11-30T03:16:56.729951+00:00","created_at":"2017-05-12T18:49:08.942882+00:00","downloads":43438,"features":{"v101":[],"v102":[],"v110":[]},"yanked":false,"license":"Apache-2.0","links":{"dependencies":"/api/v1/crates/openssl/0.9.12/dependencies","version_downloads":"/api/v1/crates/openssl/0.9.12/downloads","authors":"/api/v1/crates/openssl/0.9.12/authors"},"crate_size":null},{"id":50306,"crate":"openssl","num":"0.9.11","dl_path":"/api/v1/crates/openssl/0.9.11/download","readme_path":"/api/v1/crates/openssl/0.9.11/readme","updated_at":"2017-11-30T03:52:53.933721+00:00","created_at":"2017-04-14T23:58:01.231277+00:00","downloads":34392,"features":{"v101":[],"v102":[],"v110":[]},"yanked":false,"license":"Apache-2.0","links":{"dependencies":"/api/v1/crates/openssl/0.9.11/dependencies","version_downloads":"/api/v1/crates/openssl/0.9.11/downloads","authors":"/api/v1/crates/openssl/0.9.11/authors"},"crate_size":null},{"id":48782,"crate":"openssl","num":"0.9.10","dl_path":"/api/v1/crates/openssl/0.9.10/download","readme_path":"/api/v1/crates/openssl/0.9.10/readme","updated_at":"2017-11-30T02:23:15.113603+00:00","created_at":"2017-03-26T17:49:52.613379+00:00","downloads":25797,"features":{"v101":[],"v102":[],"v110":[]},"yanked":false,"license":"Apache-2.0","links":{"dependencies":"/api/v1/crates/openssl/0.9.10/dependencies","version_downloads":"/api/v1/crates/openssl/0.9.10/downloads","authors":"/api/v1/crates/openssl/0.9.10/authors"},"crate_size":null},{"id":47809,"crate":"openssl","num":"0.9.9","dl_path":"/api/v1/crates/openssl/0.9.9/download","readme_path":"/api/v1/crates/openssl/0.9.9/readme","updated_at":"2017-11-30T03:01:39.682615+00:00","created_at":"2017-03-14T19:56:22.058319+00:00","downloads":5758,"features":{"v101":[],"v102":[],"v110":[]},"yanked":false,"license":"Apache-2.0","links":{"dependencies":"/api/v1/crates/openssl/0.9.9/dependencies","version_downloads":"/api/v1/crates/openssl/0.9.9/downloads","authors":"/api/v1/crates/openssl/0.9.9/authors"},"crate_size":null},{"id":47398,"crate":"openssl","num":"0.9.8","dl_path":"/api/v1/crates/openssl/0.9.8/download","readme_path":"/api/v1/crates/openssl/0.9.8/readme","updated_at":"2017-11-30T02:48:47.345992+00:00","created_at":"2017-03-09T09:34:27.028751+00:00","downloads":6098,"features":{"v101":[],"v102":[],"v110":[]},"yanked":false,"license":"Apache-2.0","links":{"dependencies":"/api/v1/crates/openssl/0.9.8/dependencies","version_downloads":"/api/v1/crates/openssl/0.9.8/downloads","authors":"/api/v1/crates/openssl/0.9.8/authors"},"crate_size":null},{"id":45246,"crate":"openssl","num":"0.9.7","dl_path":"/api/v1/crates/openssl/0.9.7/download","readme_path":"/api/v1/crates/openssl/0.9.7/readme","updated_at":"2017-11-30T03:37:16.396340+00:00","created_at":"2017-02-11T22:35:19.751710+00:00","downloads":30137,"features":{"v101":[],"v102":[],"v110":[]},"yanked":false,"license":"Apache-2.0","links":{"dependencies":"/api/v1/crates/openssl/0.9.7/dependencies","version_downloads":"/api/v1/crates/openssl/0.9.7/downloads","authors":"/api/v1/crates/openssl/0.9.7/authors"},"crate_size":null},{"id":42023,"crate":"openssl","num":"0.9.6","dl_path":"/api/v1/crates/openssl/0.9.6/download","readme_path":"/api/v1/crates/openssl/0.9.6/readme","updated_at":"2017-11-30T02:46:40.497272+00:00","created_at":"2017-01-10T04:53:19.006823+00:00","downloads":34124,"features":{"v101":[],"v102":[],"v110":[]},"yanked":false,"license":"Apache-2.0","links":{"dependencies":"/api/v1/crates/openssl/0.9.6/dependencies","version_downloads":"/api/v1/crates/openssl/0.9.6/downloads","authors":"/api/v1/crates/openssl/0.9.6/authors"},"crate_size":null},{"id":41517,"crate":"openssl","num":"0.9.5","dl_path":"/api/v1/crates/openssl/0.9.5/download","readme_path":"/api/v1/crates/openssl/0.9.5/readme","updated_at":"2017-11-30T03:37:16.389326+00:00","created_at":"2017-01-04T00:10:30.135541+00:00","downloads":1870,"features":{"v101":[],"v102":[],"v110":[]},"yanked":false,"license":"Apache-2.0","links":{"dependencies":"/api/v1/crates/openssl/0.9.5/dependencies","version_downloads":"/api/v1/crates/openssl/0.9.5/downloads","authors":"/api/v1/crates/openssl/0.9.5/authors"},"crate_size":null},{"id":40256,"crate":"openssl","num":"0.9.4","dl_path":"/api/v1/crates/openssl/0.9.4/download","readme_path":"/api/v1/crates/openssl/0.9.4/readme","updated_at":"2017-11-30T03:37:15.179374+00:00","created_at":"2016-12-23T18:39:07.530816+00:00","downloads":2343,"features":{"v101":[],"v102":[],"v110":[]},"yanked":false,"license":"Apache-2.0","links":{"dependencies":"/api/v1/crates/openssl/0.9.4/dependencies","version_downloads":"/api/v1/crates/openssl/0.9.4/downloads","authors":"/api/v1/crates/openssl/0.9.4/authors"},"crate_size":null},{"id":39346,"crate":"openssl","num":"0.9.3","dl_path":"/api/v1/crates/openssl/0.9.3/download","readme_path":"/api/v1/crates/openssl/0.9.3/readme","updated_at":"2017-11-30T03:37:15.176303+00:00","created_at":"2016-12-10T05:54:43.324324+00:00","downloads":13381,"features":{"v101":[],"v102":[],"v110":[]},"yanked":false,"license":"Apache-2.0","links":{"dependencies":"/api/v1/crates/openssl/0.9.3/dependencies","version_downloads":"/api/v1/crates/openssl/0.9.3/downloads","authors":"/api/v1/crates/openssl/0.9.3/authors"},"crate_size":null},{"id":38644,"crate":"openssl","num":"0.9.2","dl_path":"/api/v1/crates/openssl/0.9.2/download","readme_path":"/api/v1/crates/openssl/0.9.2/readme","updated_at":"2017-11-30T03:37:16.375072+00:00","created_at":"2016-11-28T06:24:47.426542+00:00","downloads":3687,"features":{"v101":[],"v102":[],"v110":[]},"yanked":false,"license":"Apache-2.0","links":{"dependencies":"/api/v1/crates/openssl/0.9.2/dependencies","version_downloads":"/api/v1/crates/openssl/0.9.2/downloads","authors":"/api/v1/crates/openssl/0.9.2/authors"},"crate_size":null},{"id":37669,"crate":"openssl","num":"0.9.1","dl_path":"/api/v1/crates/openssl/0.9.1/download","readme_path":"/api/v1/crates/openssl/0.9.1/readme","updated_at":"2017-11-30T03:00:43.302153+00:00","created_at":"2016-11-11T16:47:58.606798+00:00","downloads":8527,"features":{"v101":[],"v102":[],"v110":[]},"yanked":false,"license":"Apache-2.0","links":{"dependencies":"/api/v1/crates/openssl/0.9.1/dependencies","version_downloads":"/api/v1/crates/openssl/0.9.1/downloads","authors":"/api/v1/crates/openssl/0.9.1/authors"},"crate_size":null},{"id":37347,"crate":"openssl","num":"0.9.0","dl_path":"/api/v1/crates/openssl/0.9.0/download","readme_path":"/api/v1/crates/openssl/0.9.0/readme","updated_at":"2017-11-30T03:37:15.166136+00:00","created_at":"2016-11-06T03:11:39.197825+00:00","downloads":1721,"features":{"v101":[],"v102":[],"v110":[]},"yanked":false,"license":"Apache-2.0","links":{"dependencies":"/api/v1/crates/openssl/0.9.0/dependencies","version_downloads":"/api/v1/crates/openssl/0.9.0/downloads","authors":"/api/v1/crates/openssl/0.9.0/authors"},"crate_size":null},{"id":33378,"crate":"openssl","num":"0.8.3","dl_path":"/api/v1/crates/openssl/0.8.3/download","readme_path":"/api/v1/crates/openssl/0.8.3/readme","updated_at":"2017-11-30T03:05:23.413888+00:00","created_at":"2016-09-09T16:20:41.489550+00:00","downloads":23502,"features":{"aes_ctr":["openssl-sys/aes_ctr"],"aes_xts":["openssl-sys/aes_xts"],"alpn":["openssl-sys/alpn"],"c_helpers":["gcc"],"dh_from_params":["c_helpers"],"dtlsv1":["openssl-sys/dtlsv1"],"dtlsv1_2":["openssl-sys/dtlsv1_2"],"ecdh_auto":["openssl-sys/ecdh_auto"],"hmac":["c_helpers"],"hmac_clone":["openssl-sys/hmac_clone"],"npn":["openssl-sys/npn"],"pkcs5_pbkdf2_hmac":["openssl-sys/pkcs5_pbkdf2_hmac"],"rfc5114":["openssl-sys/rfc5114"],"ssl_context_clone":["c_helpers"],"sslv2":["openssl-sys/sslv2"],"sslv3":["openssl-sys/sslv3"],"tlsv1_1":["openssl-sys/tlsv1_1"],"tlsv1_2":["openssl-sys/tlsv1_2"],"x509_clone":["c_helpers"],"x509_expiry":["c_helpers"],"x509_generator_request":["c_helpers"]},"yanked":false,"license":"Apache-2.0","links":{"dependencies":"/api/v1/crates/openssl/0.8.3/dependencies","version_downloads":"/api/v1/crates/openssl/0.8.3/downloads","authors":"/api/v1/crates/openssl/0.8.3/authors"},"crate_size":null},{"id":32000,"crate":"openssl","num":"0.8.2","dl_path":"/api/v1/crates/openssl/0.8.2/download","readme_path":"/api/v1/crates/openssl/0.8.2/readme","updated_at":"2017-11-30T02:26:50.778830+00:00","created_at":"2016-08-18T20:05:28.242523+00:00","downloads":1589,"features":{"aes_ctr":["openssl-sys/aes_ctr"],"aes_xts":["openssl-sys/aes_xts"],"alpn":["openssl-sys/alpn"],"c_helpers":["gcc"],"dh_from_params":["c_helpers"],"dtlsv1":["openssl-sys/dtlsv1"],"dtlsv1_2":["openssl-sys/dtlsv1_2"],"ecdh_auto":["openssl-sys/ecdh_auto"],"hmac":["c_helpers"],"hmac_clone":["openssl-sys/hmac_clone"],"npn":["openssl-sys/npn"],"pkcs5_pbkdf2_hmac":["openssl-sys/pkcs5_pbkdf2_hmac"],"rfc5114":["openssl-sys/rfc5114"],"ssl_context_clone":["c_helpers"],"sslv2":["openssl-sys/sslv2"],"sslv3":["openssl-sys/sslv3"],"tlsv1_1":["openssl-sys/tlsv1_1"],"tlsv1_2":["openssl-sys/tlsv1_2"],"x509_clone":["c_helpers"],"x509_expiry":["c_helpers"],"x509_generator_request":["c_helpers"]},"yanked":false,"license":"Apache-2.0","links":{"dependencies":"/api/v1/crates/openssl/0.8.2/dependencies","version_downloads":"/api/v1/crates/openssl/0.8.2/downloads","authors":"/api/v1/crates/openssl/0.8.2/authors"},"crate_size":null},{"id":31811,"crate":"openssl","num":"0.8.1","dl_path":"/api/v1/crates/openssl/0.8.1/download","readme_path":"/api/v1/crates/openssl/0.8.1/readme","updated_at":"2017-11-30T02:58:58.642815+00:00","created_at":"2016-08-16T01:51:12.582040+00:00","downloads":492,"features":{"aes_ctr":["openssl-sys/aes_ctr"],"aes_xts":["openssl-sys/aes_xts"],"alpn":["openssl-sys/alpn"],"c_helpers":["gcc"],"dh_from_params":["c_helpers"],"dtlsv1":["openssl-sys/dtlsv1"],"dtlsv1_2":["openssl-sys/dtlsv1_2"],"ecdh_auto":["openssl-sys/ecdh_auto"],"hmac":["c_helpers"],"hmac_clone":["openssl-sys/hmac_clone"],"npn":["openssl-sys/npn"],"pkcs5_pbkdf2_hmac":["openssl-sys/pkcs5_pbkdf2_hmac"],"rfc5114":["openssl-sys/rfc5114"],"ssl_context_clone":["c_helpers"],"sslv2":["openssl-sys/sslv2"],"sslv3":["openssl-sys/sslv3"],"tlsv1_1":["openssl-sys/tlsv1_1"],"tlsv1_2":["openssl-sys/tlsv1_2"],"x509_clone":["c_helpers"],"x509_generator_request":["c_helpers"]},"yanked":false,"license":"Apache-2.0","links":{"dependencies":"/api/v1/crates/openssl/0.8.1/dependencies","version_downloads":"/api/v1/crates/openssl/0.8.1/downloads","authors":"/api/v1/crates/openssl/0.8.1/authors"},"crate_size":null},{"id":31656,"crate":"openssl","num":"0.8.0","dl_path":"/api/v1/crates/openssl/0.8.0/download","readme_path":"/api/v1/crates/openssl/0.8.0/readme","updated_at":"2017-11-30T04:00:57.911769+00:00","created_at":"2016-08-12T04:14:22.558294+00:00","downloads":616,"features":{"aes_ctr":["openssl-sys/aes_ctr"],"aes_xts":["openssl-sys/aes_xts"],"alpn":["openssl-sys/alpn"],"c_helpers":["gcc"],"dh_from_params":["c_helpers"],"dtlsv1":["openssl-sys/dtlsv1"],"dtlsv1_2":["openssl-sys/dtlsv1_2"],"ecdh_auto":["openssl-sys/ecdh_auto"],"hmac":["c_helpers"],"hmac_clone":["openssl-sys/hmac_clone"],"npn":["openssl-sys/npn"],"pkcs5_pbkdf2_hmac":["openssl-sys/pkcs5_pbkdf2_hmac"],"rfc5114":["openssl-sys/rfc5114"],"ssl_context_clone":["c_helpers"],"sslv2":["openssl-sys/sslv2"],"sslv3":["openssl-sys/sslv3"],"tlsv1_1":["openssl-sys/tlsv1_1"],"tlsv1_2":["openssl-sys/tlsv1_2"],"x509_clone":["c_helpers"],"x509_generator_request":["c_helpers"]},"yanked":false,"license":"Apache-2.0","links":{"dependencies":"/api/v1/crates/openssl/0.8.0/dependencies","version_downloads":"/api/v1/crates/openssl/0.8.0/downloads","authors":"/api/v1/crates/openssl/0.8.0/authors"},"crate_size":null},{"id":29434,"crate":"openssl","num":"0.7.14","dl_path":"/api/v1/crates/openssl/0.7.14/download","readme_path":"/api/v1/crates/openssl/0.7.14/readme","updated_at":"2017-11-30T03:11:07.281141+00:00","created_at":"2016-07-01T22:46:24.720839+00:00","downloads":375767,"features":{"aes_ctr":["openssl-sys/aes_ctr"],"aes_xts":["openssl-sys/aes_xts"],"alpn":["openssl-sys/alpn"],"dtlsv1":["openssl-sys/dtlsv1"],"dtlsv1_2":["openssl-sys/dtlsv1_2"],"ecdh_auto":["openssl-sys-extras/ecdh_auto"],"nightly":[],"npn":["openssl-sys/npn"],"pkcs5_pbkdf2_hmac":["openssl-sys/pkcs5_pbkdf2_hmac"],"rfc5114":["openssl-sys/rfc5114"],"sslv2":["openssl-sys/sslv2"],"sslv3":["openssl-sys/sslv3"],"tlsv1_1":["openssl-sys/tlsv1_1"],"tlsv1_2":["openssl-sys/tlsv1_2"]},"yanked":false,"license":"Apache-2.0","links":{"dependencies":"/api/v1/crates/openssl/0.7.14/dependencies","version_downloads":"/api/v1/crates/openssl/0.7.14/downloads","authors":"/api/v1/crates/openssl/0.7.14/authors"},"crate_size":null},{"id":27465,"crate":"openssl","num":"0.7.13","dl_path":"/api/v1/crates/openssl/0.7.13/download","readme_path":"/api/v1/crates/openssl/0.7.13/readme","updated_at":"2017-11-30T03:37:16.311650+00:00","created_at":"2016-05-20T23:07:37.686085+00:00","downloads":45620,"features":{"aes_ctr":["openssl-sys/aes_ctr"],"aes_xts":["openssl-sys/aes_xts"],"alpn":["openssl-sys/alpn"],"dtlsv1":["openssl-sys/dtlsv1"],"dtlsv1_2":["openssl-sys/dtlsv1_2"],"ecdh_auto":["openssl-sys-extras/ecdh_auto"],"nightly":[],"npn":["openssl-sys/npn"],"pkcs5_pbkdf2_hmac":["openssl-sys/pkcs5_pbkdf2_hmac"],"rfc5114":["openssl-sys/rfc5114"],"sslv2":["openssl-sys/sslv2"],"sslv3":["openssl-sys/sslv3"],"tlsv1_1":["openssl-sys/tlsv1_1"],"tlsv1_2":["openssl-sys/tlsv1_2"]},"yanked":false,"license":"Apache-2.0","links":{"dependencies":"/api/v1/crates/openssl/0.7.13/dependencies","version_downloads":"/api/v1/crates/openssl/0.7.13/downloads","authors":"/api/v1/crates/openssl/0.7.13/authors"},"crate_size":null},{"id":27249,"crate":"openssl","num":"0.7.12","dl_path":"/api/v1/crates/openssl/0.7.12/download","readme_path":"/api/v1/crates/openssl/0.7.12/readme","updated_at":"2017-11-30T03:37:16.301872+00:00","created_at":"2016-05-17T06:09:46.549266+00:00","downloads":6638,"features":{"aes_ctr":["openssl-sys/aes_ctr"],"aes_xts":["openssl-sys/aes_xts"],"alpn":["openssl-sys/alpn"],"dtlsv1":["openssl-sys/dtlsv1"],"dtlsv1_2":["openssl-sys/dtlsv1_2"],"ecdh_auto":["openssl-sys-extras/ecdh_auto"],"nightly":[],"npn":["openssl-sys/npn"],"pkcs5_pbkdf2_hmac":["openssl-sys/pkcs5_pbkdf2_hmac"],"rfc5114":["openssl-sys/rfc5114"],"sslv2":["openssl-sys/sslv2"],"sslv3":["openssl-sys/sslv3"],"tlsv1_1":["openssl-sys/tlsv1_1"],"tlsv1_2":["openssl-sys/tlsv1_2"]},"yanked":false,"license":"Apache-2.0","links":{"dependencies":"/api/v1/crates/openssl/0.7.12/dependencies","version_downloads":"/api/v1/crates/openssl/0.7.12/downloads","authors":"/api/v1/crates/openssl/0.7.12/authors"},"crate_size":null},{"id":26644,"crate":"openssl","num":"0.7.11","dl_path":"/api/v1/crates/openssl/0.7.11/download","readme_path":"/api/v1/crates/openssl/0.7.11/readme","updated_at":"2017-11-30T03:02:33.291931+00:00","created_at":"2016-05-05T20:37:36.692542+00:00","downloads":11576,"features":{"aes_ctr":["openssl-sys/aes_ctr"],"aes_xts":["openssl-sys/aes_xts"],"alpn":["openssl-sys/alpn"],"dtlsv1":["openssl-sys/dtlsv1"],"dtlsv1_2":["openssl-sys/dtlsv1_2"],"ecdh_auto":["openssl-sys-extras/ecdh_auto"],"nightly":[],"npn":["openssl-sys/npn"],"pkcs5_pbkdf2_hmac":["openssl-sys/pkcs5_pbkdf2_hmac"],"rfc5114":["openssl-sys/rfc5114"],"sslv2":["openssl-sys/sslv2"],"sslv3":["openssl-sys/sslv3"],"tlsv1_1":["openssl-sys/tlsv1_1"],"tlsv1_2":["openssl-sys/tlsv1_2"]},"yanked":false,"license":"Apache-2.0","links":{"dependencies":"/api/v1/crates/openssl/0.7.11/dependencies","version_downloads":"/api/v1/crates/openssl/0.7.11/downloads","authors":"/api/v1/crates/openssl/0.7.11/authors"},"crate_size":null},{"id":25716,"crate":"openssl","num":"0.7.10","dl_path":"/api/v1/crates/openssl/0.7.10/download","readme_path":"/api/v1/crates/openssl/0.7.10/readme","updated_at":"2017-11-30T04:09:23.175909+00:00","created_at":"2016-04-17T04:01:57.647960+00:00","downloads":15879,"features":{"aes_ctr":["openssl-sys/aes_ctr"],"aes_xts":["openssl-sys/aes_xts"],"alpn":["openssl-sys/alpn"],"dtlsv1":["openssl-sys/dtlsv1"],"dtlsv1_2":["openssl-sys/dtlsv1_2"],"ecdh_auto":["openssl-sys-extras/ecdh_auto"],"nightly":[],"npn":["openssl-sys/npn"],"pkcs5_pbkdf2_hmac":["openssl-sys/pkcs5_pbkdf2_hmac"],"rfc5114":["openssl-sys/rfc5114"],"sslv2":["openssl-sys/sslv2"],"sslv3":["openssl-sys/sslv3"],"tlsv1_1":["openssl-sys/tlsv1_1"],"tlsv1_2":["openssl-sys/tlsv1_2"]},"yanked":false,"license":"Apache-2.0","links":{"dependencies":"/api/v1/crates/openssl/0.7.10/dependencies","version_downloads":"/api/v1/crates/openssl/0.7.10/downloads","authors":"/api/v1/crates/openssl/0.7.10/authors"},"crate_size":null},{"id":25161,"crate":"openssl","num":"0.7.9","dl_path":"/api/v1/crates/openssl/0.7.9/download","readme_path":"/api/v1/crates/openssl/0.7.9/readme","updated_at":"2017-11-30T02:36:50.344458+00:00","created_at":"2016-04-07T04:44:30.317123+00:00","downloads":11955,"features":{"aes_ctr":["openssl-sys/aes_ctr"],"aes_xts":["openssl-sys/aes_xts"],"alpn":["openssl-sys/alpn"],"dtlsv1":["openssl-sys/dtlsv1"],"dtlsv1_2":["openssl-sys/dtlsv1_2"],"ecdh_auto":["openssl-sys-extras/ecdh_auto"],"nightly":[],"npn":["openssl-sys/npn"],"pkcs5_pbkdf2_hmac":["openssl-sys/pkcs5_pbkdf2_hmac"],"rfc5114":["openssl-sys/rfc5114"],"sslv2":["openssl-sys/sslv2"],"sslv3":["openssl-sys/sslv3"],"tlsv1_1":["openssl-sys/tlsv1_1"],"tlsv1_2":["openssl-sys/tlsv1_2"]},"yanked":false,"license":"Apache-2.0","links":{"dependencies":"/api/v1/crates/openssl/0.7.9/dependencies","version_downloads":"/api/v1/crates/openssl/0.7.9/downloads","authors":"/api/v1/crates/openssl/0.7.9/authors"},"crate_size":null},{"id":24106,"crate":"openssl","num":"0.7.8","dl_path":"/api/v1/crates/openssl/0.7.8/download","readme_path":"/api/v1/crates/openssl/0.7.8/readme","updated_at":"2017-11-30T03:37:16.290604+00:00","created_at":"2016-03-18T16:00:16.046869+00:00","downloads":27588,"features":{"aes_ctr":["openssl-sys/aes_ctr"],"aes_xts":["openssl-sys/aes_xts"],"alpn":["openssl-sys/alpn"],"dtlsv1":["openssl-sys/dtlsv1"],"dtlsv1_2":["openssl-sys/dtlsv1_2"],"ecdh_auto":["openssl-sys-extras/ecdh_auto"],"nightly":[],"npn":["openssl-sys/npn"],"pkcs5_pbkdf2_hmac":["openssl-sys/pkcs5_pbkdf2_hmac"],"rfc5114":["openssl-sys/rfc5114"],"sslv2":["openssl-sys/sslv2"],"sslv3":["openssl-sys/sslv3"],"tlsv1_1":["openssl-sys/tlsv1_1"],"tlsv1_2":["openssl-sys/tlsv1_2"]},"yanked":false,"license":"Apache-2.0","links":{"dependencies":"/api/v1/crates/openssl/0.7.8/dependencies","version_downloads":"/api/v1/crates/openssl/0.7.8/downloads","authors":"/api/v1/crates/openssl/0.7.8/authors"},"crate_size":null},{"id":24066,"crate":"openssl","num":"0.7.7","dl_path":"/api/v1/crates/openssl/0.7.7/download","readme_path":"/api/v1/crates/openssl/0.7.7/readme","updated_at":"2017-11-30T03:40:54.561016+00:00","created_at":"2016-03-17T16:09:31.273374+00:00","downloads":962,"features":{"aes_ctr":["openssl-sys/aes_ctr"],"aes_xts":["openssl-sys/aes_xts"],"alpn":["openssl-sys/alpn"],"dtlsv1":["openssl-sys/dtlsv1"],"dtlsv1_2":["openssl-sys/dtlsv1_2"],"ecdh_auto":["openssl-sys-extras/ecdh_auto"],"nightly":[],"npn":["openssl-sys/npn"],"pkcs5_pbkdf2_hmac":["openssl-sys/pkcs5_pbkdf2_hmac"],"rfc5114":["openssl-sys/rfc5114"],"sslv2":["openssl-sys/sslv2"],"sslv3":["openssl-sys/sslv3"],"tlsv1_1":["openssl-sys/tlsv1_1"],"tlsv1_2":["openssl-sys/tlsv1_2"]},"yanked":false,"license":"Apache-2.0","links":{"dependencies":"/api/v1/crates/openssl/0.7.7/dependencies","version_downloads":"/api/v1/crates/openssl/0.7.7/downloads","authors":"/api/v1/crates/openssl/0.7.7/authors"},"crate_size":null},{"id":22170,"crate":"openssl","num":"0.7.6","dl_path":"/api/v1/crates/openssl/0.7.6/download","readme_path":"/api/v1/crates/openssl/0.7.6/readme","updated_at":"2017-11-30T03:37:16.288301+00:00","created_at":"2016-02-10T17:45:21.993468+00:00","downloads":31646,"features":{"aes_ctr":["openssl-sys/aes_ctr"],"aes_xts":["openssl-sys/aes_xts"],"alpn":["openssl-sys/alpn"],"dtlsv1":["openssl-sys/dtlsv1"],"dtlsv1_2":["openssl-sys/dtlsv1_2"],"ecdh_auto":["openssl-sys-extras/ecdh_auto"],"nightly":[],"npn":["openssl-sys/npn"],"pkcs5_pbkdf2_hmac":["openssl-sys/pkcs5_pbkdf2_hmac"],"rfc5114":["openssl-sys/rfc5114"],"sslv2":["openssl-sys/sslv2"],"sslv3":["openssl-sys/sslv3"],"tlsv1_1":["openssl-sys/tlsv1_1"],"tlsv1_2":["openssl-sys/tlsv1_2"]},"yanked":false,"license":"Apache-2.0","links":{"dependencies":"/api/v1/crates/openssl/0.7.6/dependencies","version_downloads":"/api/v1/crates/openssl/0.7.6/downloads","authors":"/api/v1/crates/openssl/0.7.6/authors"},"crate_size":null},{"id":21164,"crate":"openssl","num":"0.7.5","dl_path":"/api/v1/crates/openssl/0.7.5/download","readme_path":"/api/v1/crates/openssl/0.7.5/readme","updated_at":"2017-11-30T03:40:41.626813+00:00","created_at":"2016-01-23T00:16:44.835424+00:00","downloads":13602,"features":{"aes_ctr":["openssl-sys/aes_ctr"],"aes_xts":["openssl-sys/aes_xts"],"alpn":["openssl-sys/alpn"],"dtlsv1":["openssl-sys/dtlsv1"],"dtlsv1_2":["openssl-sys/dtlsv1_2"],"ecdh_auto":["openssl-sys-extras/ecdh_auto"],"nightly":[],"npn":["openssl-sys/npn"],"pkcs5_pbkdf2_hmac":["openssl-sys/pkcs5_pbkdf2_hmac"],"rfc5114":["openssl-sys/rfc5114"],"sslv2":["openssl-sys/sslv2"],"sslv3":["openssl-sys/sslv3"],"tlsv1_1":["openssl-sys/tlsv1_1"],"tlsv1_2":["openssl-sys/tlsv1_2"]},"yanked":false,"license":"Apache-2.0","links":{"dependencies":"/api/v1/crates/openssl/0.7.5/dependencies","version_downloads":"/api/v1/crates/openssl/0.7.5/downloads","authors":"/api/v1/crates/openssl/0.7.5/authors"},"crate_size":null},{"id":19565,"crate":"openssl","num":"0.7.4","dl_path":"/api/v1/crates/openssl/0.7.4/download","readme_path":"/api/v1/crates/openssl/0.7.4/readme","updated_at":"2017-11-30T03:01:21.551021+00:00","created_at":"2015-12-19T06:49:39.346311+00:00","downloads":16214,"features":{"aes_ctr":["openssl-sys/aes_ctr"],"aes_xts":["openssl-sys/aes_xts"],"alpn":["openssl-sys/alpn"],"dtlsv1":["openssl-sys/dtlsv1"],"dtlsv1_2":["openssl-sys/dtlsv1_2"],"ecdh_auto":["openssl-sys-extras/ecdh_auto"],"npn":["openssl-sys/npn"],"pkcs5_pbkdf2_hmac":["openssl-sys/pkcs5_pbkdf2_hmac"],"rfc5114":["openssl-sys/rfc5114"],"sslv2":["openssl-sys/sslv2"],"sslv3":["openssl-sys/sslv3"],"tlsv1_1":["openssl-sys/tlsv1_1"],"tlsv1_2":["openssl-sys/tlsv1_2"]},"yanked":false,"license":"Apache-2.0","links":{"dependencies":"/api/v1/crates/openssl/0.7.4/dependencies","version_downloads":"/api/v1/crates/openssl/0.7.4/downloads","authors":"/api/v1/crates/openssl/0.7.4/authors"},"crate_size":null},{"id":19527,"crate":"openssl","num":"0.7.3","dl_path":"/api/v1/crates/openssl/0.7.3/download","readme_path":"/api/v1/crates/openssl/0.7.3/readme","updated_at":"2017-11-30T02:25:57.948945+00:00","created_at":"2015-12-18T05:30:41.354639+00:00","downloads":564,"features":{"aes_ctr":["openssl-sys/aes_ctr"],"aes_xts":["openssl-sys/aes_xts"],"alpn":["openssl-sys/alpn"],"dtlsv1":["openssl-sys/dtlsv1"],"dtlsv1_2":["openssl-sys/dtlsv1_2"],"ecdh_auto":["openssl-sys-extras/ecdh_auto"],"npn":["openssl-sys/npn"],"pkcs5_pbkdf2_hmac":["openssl-sys/pkcs5_pbkdf2_hmac"],"rfc5114":["openssl-sys/rfc5114"],"sslv2":["openssl-sys/sslv2"],"sslv3":["openssl-sys/sslv3"],"tlsv1_1":["openssl-sys/tlsv1_1"],"tlsv1_2":["openssl-sys/tlsv1_2"]},"yanked":false,"license":"Apache-2.0","links":{"dependencies":"/api/v1/crates/openssl/0.7.3/dependencies","version_downloads":"/api/v1/crates/openssl/0.7.3/downloads","authors":"/api/v1/crates/openssl/0.7.3/authors"},"crate_size":null},{"id":19443,"crate":"openssl","num":"0.7.2","dl_path":"/api/v1/crates/openssl/0.7.2/download","readme_path":"/api/v1/crates/openssl/0.7.2/readme","updated_at":"2017-11-30T03:34:52.942862+00:00","created_at":"2015-12-16T04:07:32.601361+00:00","downloads":713,"features":{"aes_ctr":["openssl-sys/aes_ctr"],"aes_xts":["openssl-sys/aes_xts"],"alpn":["openssl-sys/alpn"],"dtlsv1":["openssl-sys/dtlsv1"],"dtlsv1_2":["openssl-sys/dtlsv1_2"],"ecdh_auto":["openssl-sys-extras/ecdh_auto"],"npn":["openssl-sys/npn"],"pkcs5_pbkdf2_hmac":["openssl-sys/pkcs5_pbkdf2_hmac"],"rfc5114":["openssl-sys/rfc5114"],"sslv2":["openssl-sys/sslv2"],"sslv3":["openssl-sys/sslv3"],"tlsv1_1":["openssl-sys/tlsv1_1"],"tlsv1_2":["openssl-sys/tlsv1_2"]},"yanked":false,"license":"Apache-2.0","links":{"dependencies":"/api/v1/crates/openssl/0.7.2/dependencies","version_downloads":"/api/v1/crates/openssl/0.7.2/downloads","authors":"/api/v1/crates/openssl/0.7.2/authors"},"crate_size":null},{"id":18678,"crate":"openssl","num":"0.7.1","dl_path":"/api/v1/crates/openssl/0.7.1/download","readme_path":"/api/v1/crates/openssl/0.7.1/readme","updated_at":"2017-11-30T03:08:06.982975+00:00","created_at":"2015-11-29T00:20:51.072658+00:00","downloads":24106,"features":{"aes_ctr":["openssl-sys/aes_ctr"],"aes_xts":["openssl-sys/aes_xts"],"alpn":["openssl-sys/alpn"],"dtlsv1":["openssl-sys/dtlsv1"],"dtlsv1_2":["openssl-sys/dtlsv1_2"],"ecdh_auto":["openssl-sys-extras/ecdh_auto"],"npn":["openssl-sys/npn"],"rfc5114":["openssl-sys/rfc5114"],"sslv2":["openssl-sys/sslv2"],"sslv3":["openssl-sys/sslv3"],"tlsv1_1":["openssl-sys/tlsv1_1"],"tlsv1_2":["openssl-sys/tlsv1_2"]},"yanked":false,"license":"Apache-2.0","links":{"dependencies":"/api/v1/crates/openssl/0.7.1/dependencies","version_downloads":"/api/v1/crates/openssl/0.7.1/downloads","authors":"/api/v1/crates/openssl/0.7.1/authors"},"crate_size":null},{"id":18208,"crate":"openssl","num":"0.7.0","dl_path":"/api/v1/crates/openssl/0.7.0/download","readme_path":"/api/v1/crates/openssl/0.7.0/readme","updated_at":"2017-11-30T03:48:16.380574+00:00","created_at":"2015-11-17T05:47:19.503371+00:00","downloads":2465,"features":{"aes_ctr":["openssl-sys/aes_ctr"],"aes_xts":["openssl-sys/aes_xts"],"alpn":["openssl-sys/alpn"],"dtlsv1":["openssl-sys/dtlsv1"],"dtlsv1_2":["openssl-sys/dtlsv1_2"],"ecdh_auto":["openssl-sys-extras/ecdh_auto"],"npn":["openssl-sys/npn"],"rfc5114":["openssl-sys/rfc5114"],"sslv2":["openssl-sys/sslv2"],"sslv3":["openssl-sys/sslv3"],"tlsv1_1":["openssl-sys/tlsv1_1"],"tlsv1_2":["openssl-sys/tlsv1_2"]},"yanked":false,"license":"Apache-2.0","links":{"dependencies":"/api/v1/crates/openssl/0.7.0/dependencies","version_downloads":"/api/v1/crates/openssl/0.7.0/downloads","authors":"/api/v1/crates/openssl/0.7.0/authors"},"crate_size":null},{"id":16708,"crate":"openssl","num":"0.6.7","dl_path":"/api/v1/crates/openssl/0.6.7/download","readme_path":"/api/v1/crates/openssl/0.6.7/readme","updated_at":"2017-11-30T02:36:10.695517+00:00","created_at":"2015-10-15T02:30:21.550775+00:00","downloads":67356,"features":{"aes_ctr":["openssl-sys/aes_ctr"],"aes_xts":["openssl-sys/aes_xts"],"alpn":["openssl-sys/alpn"],"dtlsv1":["openssl-sys/dtlsv1"],"dtlsv1_2":["openssl-sys/dtlsv1_2"],"ecdh_auto":["openssl-sys/ecdh_auto"],"npn":["openssl-sys/npn"],"rfc5114":["openssl-sys/rfc5114"],"sslv2":["openssl-sys/sslv2"],"tlsv1_1":["openssl-sys/tlsv1_1"],"tlsv1_2":["openssl-sys/tlsv1_2"]},"yanked":false,"license":"Apache-2.0","links":{"dependencies":"/api/v1/crates/openssl/0.6.7/dependencies","version_downloads":"/api/v1/crates/openssl/0.6.7/downloads","authors":"/api/v1/crates/openssl/0.6.7/authors"},"crate_size":null},{"id":16450,"crate":"openssl","num":"0.6.6","dl_path":"/api/v1/crates/openssl/0.6.6/download","readme_path":"/api/v1/crates/openssl/0.6.6/readme","updated_at":"2017-11-30T03:26:30.330013+00:00","created_at":"2015-10-05T21:46:17.779078+00:00","downloads":5510,"features":{"aes_ctr":["openssl-sys/aes_ctr"],"aes_xts":["openssl-sys/aes_xts"],"alpn":["openssl-sys/alpn"],"dtlsv1":["openssl-sys/dtlsv1"],"dtlsv1_2":["openssl-sys/dtlsv1_2"],"ecdh_auto":["openssl-sys/ecdh_auto"],"npn":["openssl-sys/npn"],"rfc5114":["openssl-sys/rfc5114"],"sslv2":["openssl-sys/sslv2"],"tlsv1_1":["openssl-sys/tlsv1_1"],"tlsv1_2":["openssl-sys/tlsv1_2"]},"yanked":false,"license":"Apache-2.0","links":{"dependencies":"/api/v1/crates/openssl/0.6.6/dependencies","version_downloads":"/api/v1/crates/openssl/0.6.6/downloads","authors":"/api/v1/crates/openssl/0.6.6/authors"},"crate_size":null},{"id":15319,"crate":"openssl","num":"0.6.5","dl_path":"/api/v1/crates/openssl/0.6.5/download","readme_path":"/api/v1/crates/openssl/0.6.5/readme","updated_at":"2017-11-30T02:42:29.302814+00:00","created_at":"2015-09-01T02:20:00.789557+00:00","downloads":18498,"features":{"aes_ctr":["openssl-sys/aes_ctr"],"aes_xts":["openssl-sys/aes_xts"],"alpn":["openssl-sys/alpn"],"dtlsv1":["openssl-sys/dtlsv1"],"dtlsv1_2":["openssl-sys/dtlsv1_2"],"npn":["openssl-sys/npn"],"sslv2":["openssl-sys/sslv2"],"tlsv1_1":["openssl-sys/tlsv1_1"],"tlsv1_2":["openssl-sys/tlsv1_2"]},"yanked":false,"license":"Apache-2.0","links":{"dependencies":"/api/v1/crates/openssl/0.6.5/dependencies","version_downloads":"/api/v1/crates/openssl/0.6.5/downloads","authors":"/api/v1/crates/openssl/0.6.5/authors"},"crate_size":null},{"id":12758,"crate":"openssl","num":"0.6.4","dl_path":"/api/v1/crates/openssl/0.6.4/download","readme_path":"/api/v1/crates/openssl/0.6.4/readme","updated_at":"2017-11-30T04:01:00.898048+00:00","created_at":"2015-07-06T18:14:24.745666+00:00","downloads":30492,"features":{"aes_xts":["openssl-sys/aes_xts"],"alpn":["openssl-sys/alpn"],"dtlsv1":["openssl-sys/dtlsv1"],"dtlsv1_2":["openssl-sys/dtlsv1_2"],"npn":["openssl-sys/npn"],"sslv2":["openssl-sys/sslv2"],"tlsv1_1":["openssl-sys/tlsv1_1"],"tlsv1_2":["openssl-sys/tlsv1_2"]},"yanked":false,"license":"Apache-2.0","links":{"dependencies":"/api/v1/crates/openssl/0.6.4/dependencies","version_downloads":"/api/v1/crates/openssl/0.6.4/downloads","authors":"/api/v1/crates/openssl/0.6.4/authors"},"crate_size":null},{"id":12295,"crate":"openssl","num":"0.6.3","dl_path":"/api/v1/crates/openssl/0.6.3/download","readme_path":"/api/v1/crates/openssl/0.6.3/readme","updated_at":"2017-11-30T03:19:56.727246+00:00","created_at":"2015-06-26T06:28:22.145634+00:00","downloads":2483,"features":{"aes_xts":["openssl-sys/aes_xts"],"dtlsv1":["openssl-sys/dtlsv1"],"dtlsv1_2":["openssl-sys/dtlsv1_2"],"npn":["openssl-sys/npn"],"sslv2":["openssl-sys/sslv2"],"tlsv1_1":["openssl-sys/tlsv1_1"],"tlsv1_2":["openssl-sys/tlsv1_2"]},"yanked":false,"license":"Apache-2.0","links":{"dependencies":"/api/v1/crates/openssl/0.6.3/dependencies","version_downloads":"/api/v1/crates/openssl/0.6.3/downloads","authors":"/api/v1/crates/openssl/0.6.3/authors"},"crate_size":null},{"id":9641,"crate":"openssl","num":"0.6.2","dl_path":"/api/v1/crates/openssl/0.6.2/download","readme_path":"/api/v1/crates/openssl/0.6.2/readme","updated_at":"2017-11-30T03:37:16.285571+00:00","created_at":"2015-04-30T16:10:41.461111+00:00","downloads":23498,"features":{"aes_xts":["openssl-sys/aes_xts"],"dtlsv1":["openssl-sys/dtlsv1"],"dtlsv1_2":["openssl-sys/dtlsv1_2"],"npn":["openssl-sys/npn"],"sslv2":["openssl-sys/sslv2"],"tlsv1_1":["openssl-sys/tlsv1_1"],"tlsv1_2":["openssl-sys/tlsv1_2"]},"yanked":false,"license":"Apache-2.0","links":{"dependencies":"/api/v1/crates/openssl/0.6.2/dependencies","version_downloads":"/api/v1/crates/openssl/0.6.2/downloads","authors":"/api/v1/crates/openssl/0.6.2/authors"},"crate_size":null},{"id":9202,"crate":"openssl","num":"0.6.1","dl_path":"/api/v1/crates/openssl/0.6.1/download","readme_path":"/api/v1/crates/openssl/0.6.1/readme","updated_at":"2017-11-30T03:53:19.548190+00:00","created_at":"2015-04-22T22:08:50.736822+00:00","downloads":3860,"features":{"aes_xts":["openssl-sys/aes_xts"],"dtlsv1":["openssl-sys/dtlsv1"],"dtlsv1_2":["openssl-sys/dtlsv1_2"],"npn":["openssl-sys/npn"],"sslv2":["openssl-sys/sslv2"],"tlsv1_1":["openssl-sys/tlsv1_1"],"tlsv1_2":["openssl-sys/tlsv1_2"]},"yanked":false,"license":"Apache-2.0","links":{"dependencies":"/api/v1/crates/openssl/0.6.1/dependencies","version_downloads":"/api/v1/crates/openssl/0.6.1/downloads","authors":"/api/v1/crates/openssl/0.6.1/authors"},"crate_size":null},{"id":8195,"crate":"openssl","num":"0.6.0","dl_path":"/api/v1/crates/openssl/0.6.0/download","readme_path":"/api/v1/crates/openssl/0.6.0/readme","updated_at":"2017-11-30T03:53:19.513047+00:00","created_at":"2015-04-05T23:50:28.373679+00:00","downloads":4429,"features":{"aes_xts":["openssl-sys/aes_xts"],"npn":["openssl-sys/npn"],"sslv2":["openssl-sys/sslv2"],"tlsv1_1":["openssl-sys/tlsv1_1"],"tlsv1_2":["openssl-sys/tlsv1_2"]},"yanked":false,"license":"Apache-2.0","links":{"dependencies":"/api/v1/crates/openssl/0.6.0/dependencies","version_downloads":"/api/v1/crates/openssl/0.6.0/downloads","authors":"/api/v1/crates/openssl/0.6.0/authors"},"crate_size":null},{"id":7959,"crate":"openssl","num":"0.5.5","dl_path":"/api/v1/crates/openssl/0.5.5/download","readme_path":"/api/v1/crates/openssl/0.5.5/readme","updated_at":"2017-11-30T04:09:23.145859+00:00","created_at":"2015-04-03T15:44:33.667216+00:00","downloads":1210,"features":{"aes_xts":["openssl-sys/aes_xts"],"npn":["openssl-sys/npn"],"sslv2":["openssl-sys/sslv2"],"tlsv1_1":["openssl-sys/tlsv1_1"],"tlsv1_2":["openssl-sys/tlsv1_2"]},"yanked":false,"license":"Apache-2.0","links":{"dependencies":"/api/v1/crates/openssl/0.5.5/dependencies","version_downloads":"/api/v1/crates/openssl/0.5.5/downloads","authors":"/api/v1/crates/openssl/0.5.5/authors"},"crate_size":null},{"id":7798,"crate":"openssl","num":"0.5.4","dl_path":"/api/v1/crates/openssl/0.5.4/download","readme_path":"/api/v1/crates/openssl/0.5.4/readme","updated_at":"2017-11-30T03:37:15.147637+00:00","created_at":"2015-04-02T18:17:27.243293+00:00","downloads":594,"features":{"aes_xts":["openssl-sys/aes_xts"],"npn":["openssl-sys/npn"],"sslv2":["openssl-sys/sslv2"],"tlsv1_1":["openssl-sys/tlsv1_1"],"tlsv1_2":["openssl-sys/tlsv1_2"]},"yanked":false,"license":"Apache-2.0","links":{"dependencies":"/api/v1/crates/openssl/0.5.4/dependencies","version_downloads":"/api/v1/crates/openssl/0.5.4/downloads","authors":"/api/v1/crates/openssl/0.5.4/authors"},"crate_size":null},{"id":7480,"crate":"openssl","num":"0.5.3","dl_path":"/api/v1/crates/openssl/0.5.3/download","readme_path":"/api/v1/crates/openssl/0.5.3/readme","updated_at":"2017-11-30T03:37:16.277423+00:00","created_at":"2015-03-29T17:21:53.955513+00:00","downloads":1394,"features":{"aes_xts":["openssl-sys/aes_xts"],"npn":["openssl-sys/npn"],"sslv2":["openssl-sys/sslv2"],"tlsv1_1":["openssl-sys/tlsv1_1"],"tlsv1_2":["openssl-sys/tlsv1_2"]},"yanked":false,"license":"Apache-2.0","links":{"dependencies":"/api/v1/crates/openssl/0.5.3/dependencies","version_downloads":"/api/v1/crates/openssl/0.5.3/downloads","authors":"/api/v1/crates/openssl/0.5.3/authors"},"crate_size":null},{"id":7118,"crate":"openssl","num":"0.5.2","dl_path":"/api/v1/crates/openssl/0.5.2/download","readme_path":"/api/v1/crates/openssl/0.5.2/readme","updated_at":"2017-11-30T03:27:12.034712+00:00","created_at":"2015-03-25T18:37:51.464849+00:00","downloads":1161,"features":{"aes_xts":["openssl-sys/aes_xts"],"npn":["openssl-sys/npn"],"sslv2":["openssl-sys/sslv2"],"tlsv1_1":["openssl-sys/tlsv1_1"],"tlsv1_2":["openssl-sys/tlsv1_2"]},"yanked":false,"license":"Apache-2.0","links":{"dependencies":"/api/v1/crates/openssl/0.5.2/dependencies","version_downloads":"/api/v1/crates/openssl/0.5.2/downloads","authors":"/api/v1/crates/openssl/0.5.2/authors"},"crate_size":null},{"id":5996,"crate":"openssl","num":"0.5.1","dl_path":"/api/v1/crates/openssl/0.5.1/download","readme_path":"/api/v1/crates/openssl/0.5.1/readme","updated_at":"2017-11-30T02:37:00.867112+00:00","created_at":"2015-03-05T18:16:04.777221+00:00","downloads":5450,"features":{"aes_xts":["openssl-sys/aes_xts"],"sslv2":["openssl-sys/sslv2"],"tlsv1_1":["openssl-sys/tlsv1_1"],"tlsv1_2":["openssl-sys/tlsv1_2"]},"yanked":false,"license":"Apache-2.0","links":{"dependencies":"/api/v1/crates/openssl/0.5.1/dependencies","version_downloads":"/api/v1/crates/openssl/0.5.1/downloads","authors":"/api/v1/crates/openssl/0.5.1/authors"},"crate_size":null},{"id":5747,"crate":"openssl","num":"0.5.0","dl_path":"/api/v1/crates/openssl/0.5.0/download","readme_path":"/api/v1/crates/openssl/0.5.0/readme","updated_at":"2017-11-30T02:45:29.987847+00:00","created_at":"2015-02-28T03:48:59.196720+00:00","downloads":1066,"features":{"aes_xts":["openssl-sys/aes_xts"],"sslv2":["openssl-sys/sslv2"],"tlsv1_1":["openssl-sys/tlsv1_1"],"tlsv1_2":["openssl-sys/tlsv1_2"]},"yanked":false,"license":"Apache-2.0","links":{"dependencies":"/api/v1/crates/openssl/0.5.0/dependencies","version_downloads":"/api/v1/crates/openssl/0.5.0/downloads","authors":"/api/v1/crates/openssl/0.5.0/authors"},"crate_size":null},{"id":5276,"crate":"openssl","num":"0.4.3","dl_path":"/api/v1/crates/openssl/0.4.3/download","readme_path":"/api/v1/crates/openssl/0.4.3/readme","updated_at":"2017-11-30T03:27:56.949972+00:00","created_at":"2015-02-20T21:44:42.271165+00:00","downloads":1533,"features":{"aes_xts":["openssl-sys/aes_xts"],"sslv2":["openssl-sys/sslv2"],"tlsv1_1":["openssl-sys/tlsv1_1"],"tlsv1_2":["openssl-sys/tlsv1_2"]},"yanked":false,"license":"Apache-2.0","links":{"dependencies":"/api/v1/crates/openssl/0.4.3/dependencies","version_downloads":"/api/v1/crates/openssl/0.4.3/downloads","authors":"/api/v1/crates/openssl/0.4.3/authors"},"crate_size":null},{"id":5217,"crate":"openssl","num":"0.4.2","dl_path":"/api/v1/crates/openssl/0.4.2/download","readme_path":"/api/v1/crates/openssl/0.4.2/readme","updated_at":"2017-11-30T04:09:24.868823+00:00","created_at":"2015-02-19T17:14:30.674468+00:00","downloads":540,"features":{"aes_xts":["openssl-sys/aes_xts"],"sslv2":["openssl-sys/sslv2"],"tlsv1_1":["openssl-sys/tlsv1_1"],"tlsv1_2":["openssl-sys/tlsv1_2"]},"yanked":false,"license":"Apache-2.0","links":{"dependencies":"/api/v1/crates/openssl/0.4.2/dependencies","version_downloads":"/api/v1/crates/openssl/0.4.2/downloads","authors":"/api/v1/crates/openssl/0.4.2/authors"},"crate_size":null},{"id":5134,"crate":"openssl","num":"0.4.1","dl_path":"/api/v1/crates/openssl/0.4.1/download","readme_path":"/api/v1/crates/openssl/0.4.1/readme","updated_at":"2017-11-30T02:43:31.975732+00:00","created_at":"2015-02-17T07:29:48.513696+00:00","downloads":539,"features":{"aes_xts":["openssl-sys/aes_xts"],"sslv2":["openssl-sys/sslv2"],"tlsv1_1":["openssl-sys/tlsv1_1"],"tlsv1_2":["openssl-sys/tlsv1_2"]},"yanked":false,"license":"Apache-2.0","links":{"dependencies":"/api/v1/crates/openssl/0.4.1/dependencies","version_downloads":"/api/v1/crates/openssl/0.4.1/downloads","authors":"/api/v1/crates/openssl/0.4.1/authors"},"crate_size":null},{"id":5042,"crate":"openssl","num":"0.4.0","dl_path":"/api/v1/crates/openssl/0.4.0/download","readme_path":"/api/v1/crates/openssl/0.4.0/readme","updated_at":"2017-11-30T03:27:08.553244+00:00","created_at":"2015-02-14T07:36:17.013219+00:00","downloads":695,"features":{"aes_xts":["openssl-sys/aes_xts"],"sslv2":["openssl-sys/sslv2"],"tlsv1_1":["openssl-sys/tlsv1_1"],"tlsv1_2":["openssl-sys/tlsv1_2"]},"yanked":false,"license":"Apache-2.0","links":{"dependencies":"/api/v1/crates/openssl/0.4.0/dependencies","version_downloads":"/api/v1/crates/openssl/0.4.0/downloads","authors":"/api/v1/crates/openssl/0.4.0/authors"},"crate_size":null},{"id":4948,"crate":"openssl","num":"0.3.6","dl_path":"/api/v1/crates/openssl/0.3.6/download","readme_path":"/api/v1/crates/openssl/0.3.6/readme","updated_at":"2017-11-30T03:00:40.923536+00:00","created_at":"2015-02-12T21:23:05.294582+00:00","downloads":652,"features":{"aes_xts":["openssl-sys/aes_xts"],"sslv2":["openssl-sys/sslv2"],"tlsv1_1":["openssl-sys/tlsv1_1"],"tlsv1_2":["openssl-sys/tlsv1_2"]},"yanked":false,"license":"Apache-2.0","links":{"dependencies":"/api/v1/crates/openssl/0.3.6/dependencies","version_downloads":"/api/v1/crates/openssl/0.3.6/downloads","authors":"/api/v1/crates/openssl/0.3.6/authors"},"crate_size":null},{"id":4891,"crate":"openssl","num":"0.3.5","dl_path":"/api/v1/crates/openssl/0.3.5/download","readme_path":"/api/v1/crates/openssl/0.3.5/readme","updated_at":"2017-11-30T03:37:16.270951+00:00","created_at":"2015-02-12T05:31:48.787281+00:00","downloads":355,"features":{"aes_xts":["openssl-sys/aes_xts"],"sslv2":["openssl-sys/sslv2"],"tlsv1_1":["openssl-sys/tlsv1_1"],"tlsv1_2":["openssl-sys/tlsv1_2"]},"yanked":false,"license":"Apache-2.0","links":{"dependencies":"/api/v1/crates/openssl/0.3.5/dependencies","version_downloads":"/api/v1/crates/openssl/0.3.5/downloads","authors":"/api/v1/crates/openssl/0.3.5/authors"},"crate_size":null},{"id":4886,"crate":"openssl","num":"0.3.4","dl_path":"/api/v1/crates/openssl/0.3.4/download","readme_path":"/api/v1/crates/openssl/0.3.4/readme","updated_at":"2017-11-30T03:37:16.268387+00:00","created_at":"2015-02-12T03:59:18.882790+00:00","downloads":265,"features":{"aes_xts":["openssl-sys/aes_xts"],"sslv2":["openssl-sys/sslv2"],"tlsv1_1":["openssl-sys/tlsv1_1"],"tlsv1_2":["openssl-sys/tlsv1_2"]},"yanked":false,"license":"Apache-2.0","links":{"dependencies":"/api/v1/crates/openssl/0.3.4/dependencies","version_downloads":"/api/v1/crates/openssl/0.3.4/downloads","authors":"/api/v1/crates/openssl/0.3.4/authors"},"crate_size":null},{"id":4776,"crate":"openssl","num":"0.3.3","dl_path":"/api/v1/crates/openssl/0.3.3/download","readme_path":"/api/v1/crates/openssl/0.3.3/readme","updated_at":"2017-11-30T03:37:15.135241+00:00","created_at":"2015-02-09T08:05:43.666991+00:00","downloads":639,"features":{"aes_xts":["openssl-sys/aes_xts"],"sslv2":["openssl-sys/sslv2"],"tlsv1_1":["openssl-sys/tlsv1_1"],"tlsv1_2":["openssl-sys/tlsv1_2"]},"yanked":false,"license":"Apache-2.0","links":{"dependencies":"/api/v1/crates/openssl/0.3.3/dependencies","version_downloads":"/api/v1/crates/openssl/0.3.3/downloads","authors":"/api/v1/crates/openssl/0.3.3/authors"},"crate_size":null},{"id":4774,"crate":"openssl","num":"0.3.2","dl_path":"/api/v1/crates/openssl/0.3.2/download","readme_path":"/api/v1/crates/openssl/0.3.2/readme","updated_at":"2017-11-30T03:37:15.130818+00:00","created_at":"2015-02-09T07:40:04.851767+00:00","downloads":1212,"features":{"aes_xts":["openssl-sys/aes_xts"],"sslv2":["openssl-sys/sslv2"],"tlsv1_1":["openssl-sys/tlsv1_1"],"tlsv1_2":["openssl-sys/tlsv1_2"]},"yanked":false,"license":"Apache-2.0","links":{"dependencies":"/api/v1/crates/openssl/0.3.2/dependencies","version_downloads":"/api/v1/crates/openssl/0.3.2/downloads","authors":"/api/v1/crates/openssl/0.3.2/authors"},"crate_size":null},{"id":4401,"crate":"openssl","num":"0.3.1","dl_path":"/api/v1/crates/openssl/0.3.1/download","readme_path":"/api/v1/crates/openssl/0.3.1/readme","updated_at":"2017-11-30T04:09:24.866965+00:00","created_at":"2015-02-03T18:10:57.926209+00:00","downloads":1137,"features":{"aes_xts":["openssl-sys/aes_xts"],"sslv2":["openssl-sys/sslv2"],"tlsv1_1":["openssl-sys/tlsv1_1"],"tlsv1_2":["openssl-sys/tlsv1_2"]},"yanked":false,"license":"Apache-2.0","links":{"dependencies":"/api/v1/crates/openssl/0.3.1/dependencies","version_downloads":"/api/v1/crates/openssl/0.3.1/downloads","authors":"/api/v1/crates/openssl/0.3.1/authors"},"crate_size":null},{"id":4387,"crate":"openssl","num":"0.3.0","dl_path":"/api/v1/crates/openssl/0.3.0/download","readme_path":"/api/v1/crates/openssl/0.3.0/readme","updated_at":"2017-11-30T04:09:24.864599+00:00","created_at":"2015-02-03T17:00:10.547052+00:00","downloads":287,"features":{"aes_xts":["openssl-sys/aes_xts"],"sslv2":["openssl-sys/sslv2"],"tlsv1_1":["openssl-sys/tlsv1_1"],"tlsv1_2":["openssl-sys/tlsv1_2"]},"yanked":false,"license":"Apache-2.0","links":{"dependencies":"/api/v1/crates/openssl/0.3.0/dependencies","version_downloads":"/api/v1/crates/openssl/0.3.0/downloads","authors":"/api/v1/crates/openssl/0.3.0/authors"},"crate_size":null},{"id":4021,"crate":"openssl","num":"0.2.18","dl_path":"/api/v1/crates/openssl/0.2.18/download","readme_path":"/api/v1/crates/openssl/0.2.18/readme","updated_at":"2017-11-30T03:37:17.423166+00:00","created_at":"2015-01-28T16:48:06.849833+00:00","downloads":2352,"features":{"aes_xts":["openssl-sys/aes_xts"],"sslv2":["openssl-sys/sslv2"],"tlsv1_1":["openssl-sys/tlsv1_1"],"tlsv1_2":["openssl-sys/tlsv1_2"]},"yanked":false,"license":"Apache-2.0","links":{"dependencies":"/api/v1/crates/openssl/0.2.18/dependencies","version_downloads":"/api/v1/crates/openssl/0.2.18/downloads","authors":"/api/v1/crates/openssl/0.2.18/authors"},"crate_size":null},{"id":3357,"crate":"openssl","num":"0.2.17","dl_path":"/api/v1/crates/openssl/0.2.17/download","readme_path":"/api/v1/crates/openssl/0.2.17/readme","updated_at":"2017-11-30T03:12:15.693249+00:00","created_at":"2015-01-23T18:22:02.650853+00:00","downloads":1083,"features":{"aes_xts":["openssl-sys/aes_xts"],"sslv2":["openssl-sys/sslv2"],"tlsv1_1":["openssl-sys/tlsv1_1"],"tlsv1_2":["openssl-sys/tlsv1_2"]},"yanked":false,"license":"Apache-2.0","links":{"dependencies":"/api/v1/crates/openssl/0.2.17/dependencies","version_downloads":"/api/v1/crates/openssl/0.2.17/downloads","authors":"/api/v1/crates/openssl/0.2.17/authors"},"crate_size":null},{"id":3044,"crate":"openssl","num":"0.2.16","dl_path":"/api/v1/crates/openssl/0.2.16/download","readme_path":"/api/v1/crates/openssl/0.2.16/readme","updated_at":"2017-11-30T03:37:15.124502+00:00","created_at":"2015-01-17T06:30:45.347167+00:00","downloads":1343,"features":{"aes_xts":["openssl-sys/aes_xts"],"sslv2":["openssl-sys/sslv2"],"tlsv1_1":["openssl-sys/tlsv1_1"],"tlsv1_2":["openssl-sys/tlsv1_2"]},"yanked":false,"license":"Apache-2.0","links":{"dependencies":"/api/v1/crates/openssl/0.2.16/dependencies","version_downloads":"/api/v1/crates/openssl/0.2.16/downloads","authors":"/api/v1/crates/openssl/0.2.16/authors"},"crate_size":null},{"id":2630,"crate":"openssl","num":"0.2.15","dl_path":"/api/v1/crates/openssl/0.2.15/download","readme_path":"/api/v1/crates/openssl/0.2.15/readme","updated_at":"2017-11-30T03:30:54.093262+00:00","created_at":"2015-01-09T18:11:41.569723+00:00","downloads":1657,"features":{"aes_xts":["openssl-sys/aes_xts"],"sslv2":["openssl-sys/sslv2"],"tlsv1_1":["openssl-sys/tlsv1_1"],"tlsv1_2":["openssl-sys/tlsv1_2"]},"yanked":false,"license":"Apache-2.0","links":{"dependencies":"/api/v1/crates/openssl/0.2.15/dependencies","version_downloads":"/api/v1/crates/openssl/0.2.15/downloads","authors":"/api/v1/crates/openssl/0.2.15/authors"},"crate_size":null},{"id":2423,"crate":"openssl","num":"0.2.14","dl_path":"/api/v1/crates/openssl/0.2.14/download","readme_path":"/api/v1/crates/openssl/0.2.14/readme","updated_at":"2017-11-30T03:37:15.122501+00:00","created_at":"2015-01-07T16:16:30.791533+00:00","downloads":507,"features":{"aes_xts":["openssl-sys/aes_xts"],"sslv2":["openssl-sys/sslv2"],"tlsv1_1":["openssl-sys/tlsv1_1"],"tlsv1_2":["openssl-sys/tlsv1_2"]},"yanked":false,"license":"Apache-2.0","links":{"dependencies":"/api/v1/crates/openssl/0.2.14/dependencies","version_downloads":"/api/v1/crates/openssl/0.2.14/downloads","authors":"/api/v1/crates/openssl/0.2.14/authors"},"crate_size":null},{"id":2335,"crate":"openssl","num":"0.2.13","dl_path":"/api/v1/crates/openssl/0.2.13/download","readme_path":"/api/v1/crates/openssl/0.2.13/readme","updated_at":"2017-11-30T03:23:00.377482+00:00","created_at":"2015-01-06T17:00:05.103560+00:00","downloads":436,"features":{"aes_xts":["openssl-sys/aes_xts"],"sslv2":["openssl-sys/sslv2"],"tlsv1_1":["openssl-sys/tlsv1_1"],"tlsv1_2":["openssl-sys/tlsv1_2"]},"yanked":false,"license":"Apache-2.0","links":{"dependencies":"/api/v1/crates/openssl/0.2.13/dependencies","version_downloads":"/api/v1/crates/openssl/0.2.13/downloads","authors":"/api/v1/crates/openssl/0.2.13/authors"},"crate_size":null},{"id":2130,"crate":"openssl","num":"0.2.12","dl_path":"/api/v1/crates/openssl/0.2.12/download","readme_path":"/api/v1/crates/openssl/0.2.12/readme","updated_at":"2017-11-30T03:27:32.934751+00:00","created_at":"2015-01-04T16:04:41.951898+00:00","downloads":554,"features":{"aes_xts":["openssl-sys/aes_xts"],"sslv2":["openssl-sys/sslv2"],"tlsv1_1":["openssl-sys/tlsv1_1"],"tlsv1_2":["openssl-sys/tlsv1_2"]},"yanked":false,"license":"Apache-2.0","links":{"dependencies":"/api/v1/crates/openssl/0.2.12/dependencies","version_downloads":"/api/v1/crates/openssl/0.2.12/downloads","authors":"/api/v1/crates/openssl/0.2.12/authors"},"crate_size":null},{"id":1994,"crate":"openssl","num":"0.2.11","dl_path":"/api/v1/crates/openssl/0.2.11/download","readme_path":"/api/v1/crates/openssl/0.2.11/readme","updated_at":"2017-11-30T03:18:19.871389+00:00","created_at":"2015-01-03T16:32:53.899811+00:00","downloads":443,"features":{"aes_xts":["openssl-sys/aes_xts"],"sslv2":["openssl-sys/sslv2"],"tlsv1_1":["openssl-sys/tlsv1_1"],"tlsv1_2":["openssl-sys/tlsv1_2"]},"yanked":false,"license":"Apache-2.0","links":{"dependencies":"/api/v1/crates/openssl/0.2.11/dependencies","version_downloads":"/api/v1/crates/openssl/0.2.11/downloads","authors":"/api/v1/crates/openssl/0.2.11/authors"},"crate_size":null},{"id":1871,"crate":"openssl","num":"0.2.10","dl_path":"/api/v1/crates/openssl/0.2.10/download","readme_path":"/api/v1/crates/openssl/0.2.10/readme","updated_at":"2017-11-30T03:56:22.718864+00:00","created_at":"2015-01-01T05:16:43.628329+00:00","downloads":516,"features":{"aes_xts":["openssl-sys/aes_xts"],"sslv2":["openssl-sys/sslv2"],"tlsv1_1":["openssl-sys/tlsv1_1"],"tlsv1_2":["openssl-sys/tlsv1_2"]},"yanked":false,"license":"Apache-2.0","links":{"dependencies":"/api/v1/crates/openssl/0.2.10/dependencies","version_downloads":"/api/v1/crates/openssl/0.2.10/downloads","authors":"/api/v1/crates/openssl/0.2.10/authors"},"crate_size":null},{"id":1798,"crate":"openssl","num":"0.2.9","dl_path":"/api/v1/crates/openssl/0.2.9/download","readme_path":"/api/v1/crates/openssl/0.2.9/readme","updated_at":"2017-11-30T03:22:42.379395+00:00","created_at":"2014-12-29T22:44:42.015689+00:00","downloads":543,"features":{"aes_xts":["openssl-sys/aes_xts"],"sslv2":["openssl-sys/sslv2"],"tlsv1_1":["openssl-sys/tlsv1_1"],"tlsv1_2":["openssl-sys/tlsv1_2"]},"yanked":false,"license":"Apache-2.0","links":{"dependencies":"/api/v1/crates/openssl/0.2.9/dependencies","version_downloads":"/api/v1/crates/openssl/0.2.9/downloads","authors":"/api/v1/crates/openssl/0.2.9/authors"},"crate_size":null},{"id":1578,"crate":"openssl","num":"0.2.8","dl_path":"/api/v1/crates/openssl/0.2.8/download","readme_path":"/api/v1/crates/openssl/0.2.8/readme","updated_at":"2017-11-30T03:28:52.302184+00:00","created_at":"2014-12-23T16:58:00.268597+00:00","downloads":951,"features":{"aes_xts":["openssl-sys/aes_xts"],"sslv2":["openssl-sys/sslv2"],"tlsv1_1":["openssl-sys/tlsv1_1"],"tlsv1_2":["openssl-sys/tlsv1_2"]},"yanked":false,"license":"Apache-2.0","links":{"dependencies":"/api/v1/crates/openssl/0.2.8/dependencies","version_downloads":"/api/v1/crates/openssl/0.2.8/downloads","authors":"/api/v1/crates/openssl/0.2.8/authors"},"crate_size":null},{"id":1467,"crate":"openssl","num":"0.2.7","dl_path":"/api/v1/crates/openssl/0.2.7/download","readme_path":"/api/v1/crates/openssl/0.2.7/readme","updated_at":"2017-11-30T03:26:52.299835+00:00","created_at":"2014-12-21T18:36:01.773912+00:00","downloads":486,"features":{"aes_xts":["openssl-sys/aes_xts"],"sslv2":["openssl-sys/sslv2"],"tlsv1_1":["openssl-sys/tlsv1_1"],"tlsv1_2":["openssl-sys/tlsv1_2"]},"yanked":false,"license":"Apache-2.0","links":{"dependencies":"/api/v1/crates/openssl/0.2.7/dependencies","version_downloads":"/api/v1/crates/openssl/0.2.7/downloads","authors":"/api/v1/crates/openssl/0.2.7/authors"},"crate_size":null},{"id":1367,"crate":"openssl","num":"0.2.6","dl_path":"/api/v1/crates/openssl/0.2.6/download","readme_path":"/api/v1/crates/openssl/0.2.6/readme","updated_at":"2017-11-30T03:37:17.420649+00:00","created_at":"2014-12-19T16:22:09.458924+00:00","downloads":420,"features":{"aes_xts":["openssl-sys/aes_xts"],"sslv2":["openssl-sys/sslv2"],"tlsv1_1":["openssl-sys/tlsv1_1"],"tlsv1_2":["openssl-sys/tlsv1_2"]},"yanked":false,"license":"Apache-2.0","links":{"dependencies":"/api/v1/crates/openssl/0.2.6/dependencies","version_downloads":"/api/v1/crates/openssl/0.2.6/downloads","authors":"/api/v1/crates/openssl/0.2.6/authors"},"crate_size":null},{"id":1208,"crate":"openssl","num":"0.2.5","dl_path":"/api/v1/crates/openssl/0.2.5/download","readme_path":"/api/v1/crates/openssl/0.2.5/readme","updated_at":"2017-11-30T03:37:16.250028+00:00","created_at":"2014-12-16T16:57:07.805835+00:00","downloads":462,"features":{"aes_xts":["openssl-sys/aes_xts"],"sslv2":["openssl-sys/sslv2"],"tlsv1_1":["openssl-sys/tlsv1_1"],"tlsv1_2":["openssl-sys/tlsv1_2"]},"yanked":false,"license":"Apache-2.0","links":{"dependencies":"/api/v1/crates/openssl/0.2.5/dependencies","version_downloads":"/api/v1/crates/openssl/0.2.5/downloads","authors":"/api/v1/crates/openssl/0.2.5/authors"},"crate_size":null},{"id":1168,"crate":"openssl","num":"0.2.4","dl_path":"/api/v1/crates/openssl/0.2.4/download","readme_path":"/api/v1/crates/openssl/0.2.4/readme","updated_at":"2017-11-30T03:19:06.822506+00:00","created_at":"2014-12-15T17:26:38.562669+00:00","downloads":363,"features":{"aes_xts":["openssl-sys/aes_xts"],"sslv2":["openssl-sys/sslv2"],"tlsv1_1":["openssl-sys/tlsv1_1"],"tlsv1_2":["openssl-sys/tlsv1_2"]},"yanked":false,"license":"Apache-2.0","links":{"dependencies":"/api/v1/crates/openssl/0.2.4/dependencies","version_downloads":"/api/v1/crates/openssl/0.2.4/downloads","authors":"/api/v1/crates/openssl/0.2.4/authors"},"crate_size":null},{"id":1029,"crate":"openssl","num":"0.2.3","dl_path":"/api/v1/crates/openssl/0.2.3/download","readme_path":"/api/v1/crates/openssl/0.2.3/readme","updated_at":"2017-11-30T03:19:06.812333+00:00","created_at":"2014-12-12T04:11:20.715265+00:00","downloads":705,"features":{"aes_xts":["openssl-sys/aes_xts"],"sslv2":["openssl-sys/sslv2"],"tlsv1_1":["openssl-sys/tlsv1_1"],"tlsv1_2":["openssl-sys/tlsv1_2"]},"yanked":false,"license":"Apache-2.0","links":{"dependencies":"/api/v1/crates/openssl/0.2.3/dependencies","version_downloads":"/api/v1/crates/openssl/0.2.3/downloads","authors":"/api/v1/crates/openssl/0.2.3/authors"},"crate_size":null},{"id":764,"crate":"openssl","num":"0.2.2","dl_path":"/api/v1/crates/openssl/0.2.2/download","readme_path":"/api/v1/crates/openssl/0.2.2/readme","updated_at":"2017-11-30T03:53:13.558922+00:00","created_at":"2014-12-01T21:24:12.367221+00:00","downloads":797,"features":{"aes_xts":["openssl-sys/aes_xts"],"sslv2":["openssl-sys/sslv2"],"tlsv1_1":["openssl-sys/tlsv1_1"],"tlsv1_2":["openssl-sys/tlsv1_2"]},"yanked":false,"license":"Apache-2.0","links":{"dependencies":"/api/v1/crates/openssl/0.2.2/dependencies","version_downloads":"/api/v1/crates/openssl/0.2.2/downloads","authors":"/api/v1/crates/openssl/0.2.2/authors"},"crate_size":null},{"id":727,"crate":"openssl","num":"0.2.1","dl_path":"/api/v1/crates/openssl/0.2.1/download","readme_path":"/api/v1/crates/openssl/0.2.1/readme","updated_at":"2017-11-30T03:53:13.556884+00:00","created_at":"2014-11-28T23:49:55.089830+00:00","downloads":414,"features":{"aes_xts":["openssl-sys/aes_xts"],"sslv2":["openssl-sys/sslv2"],"tlsv1_1":["openssl-sys/tlsv1_1"],"tlsv1_2":["openssl-sys/tlsv1_2"]},"yanked":false,"license":"Apache-2.0","links":{"dependencies":"/api/v1/crates/openssl/0.2.1/dependencies","version_downloads":"/api/v1/crates/openssl/0.2.1/downloads","authors":"/api/v1/crates/openssl/0.2.1/authors"},"crate_size":null},{"id":701,"crate":"openssl","num":"0.2.0","dl_path":"/api/v1/crates/openssl/0.2.0/download","readme_path":"/api/v1/crates/openssl/0.2.0/readme","updated_at":"2017-11-30T03:23:47.359369+00:00","created_at":"2014-11-28T05:37:38.580760+00:00","downloads":307,"features":{"aes_xts":["openssl-sys/aes_xts"],"sslv2":["openssl-sys/sslv2"],"tlsv1_1":["openssl-sys/tlsv1_1"],"tlsv1_2":["openssl-sys/tlsv1_2"]},"yanked":false,"license":"Apache-2.0","links":{"dependencies":"/api/v1/crates/openssl/0.2.0/dependencies","version_downloads":"/api/v1/crates/openssl/0.2.0/downloads","authors":"/api/v1/crates/openssl/0.2.0/authors"},"crate_size":null},{"id":650,"crate":"openssl","num":"0.1.1","dl_path":"/api/v1/crates/openssl/0.1.1/download","readme_path":"/api/v1/crates/openssl/0.1.1/readme","updated_at":"2017-11-30T03:53:11.622543+00:00","created_at":"2014-11-26T16:50:23.567453+00:00","downloads":379,"features":{"aes_xts":["openssl-sys/aes_xts"],"sslv2":["openssl-sys/sslv2"],"tlsv1_1":["openssl-sys/tlsv1_1"],"tlsv1_2":["openssl-sys/tlsv1_2"]},"yanked":false,"license":"Apache-2.0","links":{"dependencies":"/api/v1/crates/openssl/0.1.1/dependencies","version_downloads":"/api/v1/crates/openssl/0.1.1/downloads","authors":"/api/v1/crates/openssl/0.1.1/authors"},"crate_size":null},{"id":631,"crate":"openssl","num":"0.1.0","dl_path":"/api/v1/crates/openssl/0.1.0/download","readme_path":"/api/v1/crates/openssl/0.1.0/readme","updated_at":"2017-11-30T03:37:15.118931+00:00","created_at":"2014-11-26T00:47:22.347499+00:00","downloads":327,"features":{"aes_xts":["openssl-sys/aes_xts"],"sslv2":["openssl-sys/sslv2"],"tlsv1_1":["openssl-sys/tlsv1_1"],"tlsv1_2":["openssl-sys/tlsv1_2"]},"yanked":false,"license":"Apache-2.0","links":{"dependencies":"/api/v1/crates/openssl/0.1.0/dependencies","version_downloads":"/api/v1/crates/openssl/0.1.0/downloads","authors":"/api/v1/crates/openssl/0.1.0/authors"},"crate_size":null},{"id":581,"crate":"openssl","num":"0.0.2","dl_path":"/api/v1/crates/openssl/0.0.2/download","readme_path":"/api/v1/crates/openssl/0.0.2/readme","updated_at":"2017-11-30T03:37:15.116472+00:00","created_at":"2014-11-24T02:30:36.227158+00:00","downloads":445,"features":{"aes_xts":["openssl-sys/aes_xts"],"sslv2":["openssl-sys/sslv2"],"tlsv1_1":["openssl-sys/tlsv1_1"],"tlsv1_2":["openssl-sys/tlsv1_2"]},"yanked":false,"license":"Apache-2.0","links":{"dependencies":"/api/v1/crates/openssl/0.0.2/dependencies","version_downloads":"/api/v1/crates/openssl/0.0.2/downloads","authors":"/api/v1/crates/openssl/0.0.2/authors"},"crate_size":null},{"id":321,"crate":"openssl","num":"0.0.1","dl_path":"/api/v1/crates/openssl/0.0.1/download","readme_path":"/api/v1/crates/openssl/0.0.1/readme","updated_at":"2017-11-30T03:37:15.114387+00:00","created_at":"2014-11-21T06:54:00.713138+00:00","downloads":264,"features":{},"yanked":true,"license":"Apache-2.0","links":{"dependencies":"/api/v1/crates/openssl/0.0.1/dependencies","version_downloads":"/api/v1/crates/openssl/0.0.1/downloads","authors":"/api/v1/crates/openssl/0.0.1/authors"},"crate_size":null}],"keywords":[{"id":"tls","keyword":"tls","created_at":"2014-11-24T02:30:36.426701+00:00","crates_cnt":37},{"id":"ssl","keyword":"ssl","created_at":"2014-11-24T02:30:36.439542+00:00","crates_cnt":23},{"id":"dtls","keyword":"dtls","created_at":"2015-04-22T22:08:50.934952+00:00","crates_cnt":3},{"id":"crypto","keyword":"crypto","created_at":"2014-11-24T02:30:36.413823+00:00","crates_cnt":221}],"categories":[{"id":"cryptography","category":"Cryptography","slug":"cryptography","description":"Algorithms intended for securing data.","created_at":"2017-01-17T19:13:05.112025+00:00","crates_cnt":297},{"id":"api-bindings","category":"API bindings","slug":"api-bindings","description":"Idiomatic wrappers of specific APIs for convenient access from Rust. Includes HTTP API wrappers as well. Non-idiomatic or unsafe bindings can be found in External FFI bindings.","created_at":"2017-01-17T19:13:05.112025+00:00","crates_cnt":527}]}