{"crate":{"created_at":"2016-02-14T18:48:45Z","description":"A simple Redis-based task queue","documentation":"https://badboy.github.io/oppgave","downloads":399,"homepage":"https://github.com/badboy/oppgave","id":"oppgave","keywords":["queue","redis"],"license":"MIT","links":{"owners":"/api/v1/crates/oppgave/owners","reverse_dependencies":"/api/v1/crates/oppgave/reverse_dependencies","version_downloads":"/api/v1/crates/oppgave/downloads","versions":null},"max_version":"0.1.0","name":"oppgave","repository":"https://github.com/badboy/oppgave","updated_at":"2016-02-14T18:48:45Z","versions":[22367]},"keywords":[{"crates_cnt":21,"created_at":"2014-11-23T17:40:16Z","id":"queue","keyword":"queue"},{"crates_cnt":13,"created_at":"2014-11-21T15:32:46Z","id":"redis","keyword":"redis"}],"versions":[{"crate":"oppgave","created_at":"2016-02-14T18:48:45Z","dl_path":"/api/v1/crates/oppgave/0.1.0/download","downloads":399,"features":{},"id":22367,"links":{"authors":"/api/v1/crates/oppgave/0.1.0/authors","dependencies":"/api/v1/crates/oppgave/0.1.0/dependencies","version_downloads":"/api/v1/crates/oppgave/0.1.0/downloads"},"num":"0.1.0","updated_at":"2016-02-14T18:48:45Z","yanked":false}]}